{
  "data": [
    {
      "city": "Chicomuselo",
      "colonia": "20 de Noviembre",
      "postal_code": [
        "30123"
      ]
    },
    {
      "city": "Chicomuselo",
      "colonia": "Chaschahual",
      "postal_code": [
        "30120"
      ]
    },
    {
      "city": "Chicomuselo",
      "colonia": "Chicomuselo",
      "postal_code": [
        "30120"
      ]
    },
    {
      "city": "Chicomuselo",
      "colonia": "El Naranjo",
      "postal_code": [
        "30123"
      ]
    },
    {
      "city": "Chicomuselo",
      "colonia": "El Raizal",
      "postal_code": [
        "30129"
      ]
    },
    {
      "city": "Chicomuselo",
      "colonia": "El Regadillo",
      "postal_code": [
        "30126"
      ]
    },
    {
      "city": "Chicomuselo",
      "colonia": "Las Flores",
      "postal_code": [
        "30121"
      ]
    },
    {
      "city": "Chicomuselo",
      "colonia": "Lazaro Cardenas",
      "postal_code": [
        "30120"
      ]
    },
    {
      "city": "Chicomuselo",
      "colonia": "Miguel Aleman",
      "postal_code": [
        "30124"
      ]
    },
    {
      "city": "Chicomuselo",
      "colonia": "Nueva America",
      "postal_code": [
        "30129"
      ]
    },
    {
      "city": "Chicomuselo",
      "colonia": "Nueva Reforma",
      "postal_code": [
        "30129"
      ]
    },
    {
      "city": "Chicomuselo",
      "colonia": "Nuevo Morelia",
      "postal_code": [
        "30124"
      ]
    },
    {
      "city": "Chicomuselo",
      "colonia": "Pablo L Sidar",
      "postal_code": [
        "30120"
      ]
    },
    {
      "city": "Chicomuselo",
      "colonia": "Piedra Labrada",
      "postal_code": [
        "30120"
      ]
    },
    {
      "city": "Chicomuselo",
      "colonia": "Potrerillos",
      "postal_code": [
        "30125"
      ]
    },
    {
      "city": "Chicomuselo",
      "colonia": "San Jose Monte Sinai",
      "postal_code": [
        "30120"
      ]
    },
    {
      "city": "Chicomuselo",
      "colonia": "Santa Elena",
      "postal_code": [
        "30124"
      ]
    },
    {
      "city": "Chicomuselo",
      "colonia": "Vida Mejor",
      "postal_code": [
        "30120"
      ]
    },
    {
      "city": "Chicomuselo",
      "colonia": "Zacualpa",
      "postal_code": [
        "30123"
      ]
    }
  ]
}