{
  "data": [
    {
      "city": "Comalcalco",
      "colonia": "Adolfo Lopez Mateos",
      "postal_code": [
        "86323"
      ]
    },
    {
      "city": "Comalcalco",
      "colonia": "Aldama",
      "postal_code": [
        "86640"
      ]
    },
    {
      "city": "Comalcalco",
      "colonia": "Aldama 2da. Seccion (Fernando Segovia)",
      "postal_code": [
        "86640"
      ]
    },
    {
      "city": "Comalcalco",
      "colonia": "Aldama 3ra. Seccion (Huapacalito)",
      "postal_code": [
        "86640"
      ]
    },
    {
      "city": "Comalcalco",
      "colonia": "Aldama 4ta. Seccion (El Naranjito)",
      "postal_code": [
        "86640"
      ]
    },
    {
      "city": "Comalcalco",
      "colonia": "Arena 1ra. Seccion",
      "postal_code": [
        "86660"
      ]
    },
    {
      "city": "Comalcalco",
      "colonia": "Arena 2a Secc",
      "postal_code": [
        "86660"
      ]
    },
    {
      "city": "Comalcalco",
      "colonia": "Arena 3ra. Seccion",
      "postal_code": [
        "86660"
      ]
    },
    {
      "city": "Comalcalco",
      "colonia": "Arena 4ta. Seccion",
      "postal_code": [
        "86660"
      ]
    },
    {
      "city": "Comalcalco",
      "colonia": "Arena 5a Seccion",
      "postal_code": [
        "86660"
      ]
    },
    {
      "city": "Comalcalco",
      "colonia": "Arena 6ta Seccion (La Bolsa)",
      "postal_code": [
        "86660"
      ]
    },
    {
      "city": "Comalcalco",
      "colonia": "Arroyo Hondo 1ra. Seccion (Guacimo)",
      "postal_code": [
        "86660"
      ]
    },
    {
      "city": "Comalcalco",
      "colonia": "Arroyo Hondo 2da. Seccion",
      "postal_code": [
        "86660"
      ]
    },
    {
      "city": "Comalcalco",
      "colonia": "Arroyo Hondo 3a Secc",
      "postal_code": [
        "86660"
      ]
    },
    {
      "city": "Comalcalco",
      "colonia": "Arroyo Hondo 4ta. Seccion",
      "postal_code": [
        "86630"
      ]
    },
    {
      "city": "Comalcalco",
      "colonia": "Asturias",
      "postal_code": [
        "86357"
      ]
    },
    {
      "city": "Comalcalco",
      "colonia": "Belen",
      "postal_code": [
        "86320"
      ]
    },
    {
      "city": "Comalcalco",
      "colonia": "Belisario Dominguez",
      "postal_code": [
        "86640"
      ]
    },
    {
      "city": "Comalcalco",
      "colonia": "Betania",
      "postal_code": [
        "86640"
      ]
    },
    {
      "city": "Comalcalco",
      "colonia": "Bicentenario",
      "postal_code": [
        "86340"
      ]
    },
    {
      "city": "Comalcalco",
      "colonia": "Buenavista",
      "postal_code": [
        "86357"
      ]
    },
    {
      "city": "Comalcalco",
      "colonia": "Carlos Greene",
      "postal_code": [
        "86660"
      ]
    },
    {
      "city": "Comalcalco",
      "colonia": "Carlos Greene 2da. Seccion",
      "postal_code": [
        "86660"
      ]
    },
    {
      "city": "Comalcalco",
      "colonia": "Carlos Greene 3a Seccion",
      "postal_code": [
        "86630"
      ]
    },
    {
      "city": "Comalcalco",
      "colonia": "Carlos Greene 4a Seccion",
      "postal_code": [
        "86630"
      ]
    },
    {
      "city": "Comalcalco",
      "colonia": "Carlos Pellicer Camara",
      "postal_code": [
        "86670"
      ]
    },
    {
      "city": "Comalcalco",
      "colonia": "Centro Tular 1ra. Seccion",
      "postal_code": [
        "86643"
      ]
    },
    {
      "city": "Comalcalco",
      "colonia": "Centro Tular 2da. Seccion",
      "postal_code": [
        "86643"
      ]
    },
    {
      "city": "Comalcalco",
      "colonia": "Champa de Cupilco",
      "postal_code": [
        "86670"
      ]
    },
    {
      "city": "Comalcalco",
      "colonia": "Chichicapa",
      "postal_code": [
        "86670"
      ]
    },
    {
      "city": "Comalcalco",
      "colonia": "Chicozapote",
      "postal_code": [
        "86643"
      ]
    },
    {
      "city": "Comalcalco",
      "colonia": "Cocohital",
      "postal_code": [
        "86645"
      ]
    },
    {
      "city": "Comalcalco",
      "colonia": "Comalcalco Centro",
      "postal_code": [
        "86300"
      ]
    },
    {
      "city": "Comalcalco",
      "colonia": "Conjunto Habitacional Presidentes",
      "postal_code": [
        "86320"
      ]
    },
    {
      "city": "Comalcalco",
      "colonia": "Conjunto Habitacional Presidentes 2",
      "postal_code": [
        "86320"
      ]
    },
    {
      "city": "Comalcalco",
      "colonia": "Cupilco",
      "postal_code": [
        "86670"
      ]
    },
    {
      "city": "Comalcalco",
      "colonia": "Cuxcuxapa",
      "postal_code": [
        "86670"
      ]
    },
    {
      "city": "Comalcalco",
      "colonia": "Delicias",
      "postal_code": [
        "86370"
      ]
    },
    {
      "city": "Comalcalco",
      "colonia": "Ecologica Lic. Carlos A. Madrazo Becerra",
      "postal_code": [
        "86325"
      ]
    },
    {
      "city": "Comalcalco",
      "colonia": "El angel",
      "postal_code": [
        "86670"
      ]
    },
    {
      "city": "Comalcalco",
      "colonia": "Emiliano Zapata 1ra. Seccion",
      "postal_code": [
        "86630"
      ]
    },
    {
      "city": "Comalcalco",
      "colonia": "Emiliano Zapata 2da. Seccion",
      "postal_code": [
        "86630"
      ]
    },
    {
      "city": "Comalcalco",
      "colonia": "Empleado de Confianza",
      "postal_code": [
        "86389"
      ]
    },
    {
      "city": "Comalcalco",
      "colonia": "Fovissste",
      "postal_code": [
        "86389"
      ]
    },
    {
      "city": "Comalcalco",
      "colonia": "Francisco I Madero 1a Secc",
      "postal_code": [
        "86640"
      ]
    },
    {
      "city": "Comalcalco",
      "colonia": "Francisco I Madero 2a Secc",
      "postal_code": [
        "86640"
      ]
    },
    {
      "city": "Comalcalco",
      "colonia": "Francisco Trujillo Gurria",
      "postal_code": [
        "86670"
      ]
    },
    {
      "city": "Comalcalco",
      "colonia": "Gobernadores",
      "postal_code": [
        "86670"
      ]
    },
    {
      "city": "Comalcalco",
      "colonia": "Gregorio Mendez 1ra. Seccion",
      "postal_code": [
        "86655"
      ]
    },
    {
      "city": "Comalcalco",
      "colonia": "Gregorio Mendez 2da. Seccion",
      "postal_code": [
        "86640"
      ]
    },
    {
      "city": "Comalcalco",
      "colonia": "Gregorio Mendez 3a Secc",
      "postal_code": [
        "86640"
      ]
    },
    {
      "city": "Comalcalco",
      "colonia": "Gregorio Mendez 4ta. Seccion (El Santiago)",
      "postal_code": [
        "86652"
      ]
    },
    {
      "city": "Comalcalco",
      "colonia": "Guatemalan",
      "postal_code": [
        "86654"
      ]
    },
    {
      "city": "Comalcalco",
      "colonia": "Guayo 1ra Seccion",
      "postal_code": [
        "86630"
      ]
    },
    {
      "city": "Comalcalco",
      "colonia": "Guayo 2da Seccion",
      "postal_code": [
        "86630"
      ]
    },
    {
      "city": "Comalcalco",
      "colonia": "Guayo 3ra Seccion",
      "postal_code": [
        "86630"
      ]
    },
    {
      "city": "Comalcalco",
      "colonia": "Gustavo de La Fuente Dorantes",
      "postal_code": [
        "86320"
      ]
    },
    {
      "city": "Comalcalco",
      "colonia": "Hermenegildo Galeana",
      "postal_code": [
        "86630"
      ]
    },
    {
      "city": "Comalcalco",
      "colonia": "Ignacio Gutierrez Gomez",
      "postal_code": [
        "86630"
      ]
    },
    {
      "city": "Comalcalco",
      "colonia": "Ignacio Zaragoza 1ra. Seccion",
      "postal_code": [
        "86644"
      ]
    },
    {
      "city": "Comalcalco",
      "colonia": "Ignacio Zaragoza 2da. Seccion",
      "postal_code": [
        "86644"
      ]
    },
    {
      "city": "Comalcalco",
      "colonia": "Ignacio Zaragoza 3ra. Seccion",
      "postal_code": [
        "86645"
      ]
    },
    {
      "city": "Comalcalco",
      "colonia": "Ignacio Zaragoza 4ta. Seccion (San Andres)",
      "postal_code": [
        "86644"
      ]
    },
    {
      "city": "Comalcalco",
      "colonia": "Independencia 1ra. Seccion",
      "postal_code": [
        "86650"
      ]
    },
    {
      "city": "Comalcalco",
      "colonia": "Independencia 2a Secc",
      "postal_code": [
        "86670"
      ]
    },
    {
      "city": "Comalcalco",
      "colonia": "Independencia 3a Seccion",
      "postal_code": [
        "86670"
      ]
    },
    {
      "city": "Comalcalco",
      "colonia": "Infonavit",
      "postal_code": [
        "86320"
      ]
    },
    {
      "city": "Comalcalco",
      "colonia": "Jesus Carranza",
      "postal_code": [
        "86670"
      ]
    },
    {
      "city": "Comalcalco",
      "colonia": "Jorge Diaz Serrano",
      "postal_code": [
        "86360"
      ]
    },
    {
      "city": "Comalcalco",
      "colonia": "Jose Maria Pino Suarez 1ra. Seccion",
      "postal_code": [
        "86643"
      ]
    },
    {
      "city": "Comalcalco",
      "colonia": "Jose Maria Pino Suarez 2da. Seccion",
      "postal_code": [
        "86643"
      ]
    },
    {
      "city": "Comalcalco",
      "colonia": "Jose Maria Pino Suarez 3ra. Seccion (Corinto)",
      "postal_code": [
        "86643"
      ]
    },
    {
      "city": "Comalcalco",
      "colonia": "La Escondida",
      "postal_code": [
        "86360"
      ]
    },
    {
      "city": "Comalcalco",
      "colonia": "La Esperanza",
      "postal_code": [
        "86357"
      ]
    },
    {
      "city": "Comalcalco",
      "colonia": "Lagartera",
      "postal_code": [
        "86670"
      ]
    },
    {
      "city": "Comalcalco",
      "colonia": "La Joya",
      "postal_code": [
        "86380"
      ]
    },
    {
      "city": "Comalcalco",
      "colonia": "La Quinta",
      "postal_code": [
        "86670"
      ]
    },
    {
      "city": "Comalcalco",
      "colonia": "Las Brisas",
      "postal_code": [
        "86388"
      ]
    },
    {
      "city": "Comalcalco",
      "colonia": "Las Rosas",
      "postal_code": [
        "86360"
      ]
    },
    {
      "city": "Comalcalco",
      "colonia": "Lazaro Cardenas 1a Secc",
      "postal_code": [
        "86630"
      ]
    },
    {
      "city": "Comalcalco",
      "colonia": "Lazaro Cardenas 2da. Seccion (El Retiro)",
      "postal_code": [
        "86630"
      ]
    },
    {
      "city": "Comalcalco",
      "colonia": "Lazaro Cardenas 3ra. Seccion",
      "postal_code": [
        "86630"
      ]
    },
    {
      "city": "Comalcalco",
      "colonia": "Lazaro Cardenas Del Rio",
      "postal_code": [
        "86389"
      ]
    },
    {
      "city": "Comalcalco",
      "colonia": "Leon Zarate 1ra. Seccion",
      "postal_code": [
        "86640"
      ]
    },
    {
      "city": "Comalcalco",
      "colonia": "Leon Zarate 2da. Seccion",
      "postal_code": [
        "86640"
      ]
    },
    {
      "city": "Comalcalco",
      "colonia": "Magisterial",
      "postal_code": [
        "86325"
      ]
    },
    {
      "city": "Comalcalco",
      "colonia": "Magisterial 2",
      "postal_code": [
        "86340"
      ]
    },
    {
      "city": "Comalcalco",
      "colonia": "Miguel Hidalgo",
      "postal_code": [
        "86640"
      ]
    },
    {
      "city": "Comalcalco",
      "colonia": "Morelos",
      "postal_code": [
        "86389"
      ]
    },
    {
      "city": "Comalcalco",
      "colonia": "Norte 1ra. Seccion (Buena Vista)",
      "postal_code": [
        "86670"
      ]
    },
    {
      "city": "Comalcalco",
      "colonia": "Norte 2a Secc",
      "postal_code": [
        "86650"
      ]
    },
    {
      "city": "Comalcalco",
      "colonia": "Novillero 4a Seccion",
      "postal_code": [
        "86670"
      ]
    },
    {
      "city": "Comalcalco",
      "colonia": "Occidente 1a Secc",
      "postal_code": [
        "86650"
      ]
    },
    {
      "city": "Comalcalco",
      "colonia": "Occidente 2a Secc",
      "postal_code": [
        "86650"
      ]
    },
    {
      "city": "Comalcalco",
      "colonia": "Occidente 3a Seccion",
      "postal_code": [
        "86650"
      ]
    },
    {
      "city": "Comalcalco",
      "colonia": "Occidente 4a Seccion",
      "postal_code": [
        "86650"
      ]
    },
    {
      "city": "Comalcalco",
      "colonia": "Oriente 1a Secc (Santo Domingo)",
      "postal_code": [
        "86670"
      ]
    },
    {
      "city": "Comalcalco",
      "colonia": "Oriente 1ra. Seccion",
      "postal_code": [
        "86670"
      ]
    },
    {
      "city": "Comalcalco",
      "colonia": "Oriente 2da. Seccion (San Cayetano)",
      "postal_code": [
        "86658"
      ]
    },
    {
      "city": "Comalcalco",
      "colonia": "Oriente 3a Secc",
      "postal_code": [
        "86658"
      ]
    },
    {
      "city": "Comalcalco",
      "colonia": "Oriente 4ta. Seccion (Tripa Ciega)",
      "postal_code": [
        "86658"
      ]
    },
    {
      "city": "Comalcalco",
      "colonia": "Oriente 5a Secc (La Candelaria)",
      "postal_code": [
        "86658"
      ]
    },
    {
      "city": "Comalcalco",
      "colonia": "Oriente 6ta. Seccion (Los Mulatos)",
      "postal_code": [
        "86658"
      ]
    },
    {
      "city": "Comalcalco",
      "colonia": "Palma Real",
      "postal_code": [
        "86320"
      ]
    },
    {
      "city": "Comalcalco",
      "colonia": "Paso de Cupilco",
      "postal_code": [
        "86670"
      ]
    },
    {
      "city": "Comalcalco",
      "colonia": "Patastal 1ra. Seccion",
      "postal_code": [
        "86644"
      ]
    },
    {
      "city": "Comalcalco",
      "colonia": "Patastal 2da. Seccion",
      "postal_code": [
        "86644"
      ]
    },
    {
      "city": "Comalcalco",
      "colonia": "Patastal 3ra. Seccion",
      "postal_code": [
        "86644"
      ]
    },
    {
      "city": "Comalcalco",
      "colonia": "PEMEX (Cobertizo)",
      "postal_code": [
        "86388"
      ]
    },
    {
      "city": "Comalcalco",
      "colonia": "Potrerillo",
      "postal_code": [
        "86670"
      ]
    },
    {
      "city": "Comalcalco",
      "colonia": "Progreso Tular 1ra. Seccion",
      "postal_code": [
        "86643"
      ]
    },
    {
      "city": "Comalcalco",
      "colonia": "Progreso Tular 2da. Seccion",
      "postal_code": [
        "86643"
      ]
    },
    {
      "city": "Comalcalco",
      "colonia": "Reyes Hernandez 1ra. Seccion",
      "postal_code": [
        "86640"
      ]
    },
    {
      "city": "Comalcalco",
      "colonia": "Reyes Hernandez 2da. Seccion",
      "postal_code": [
        "86655"
      ]
    },
    {
      "city": "Comalcalco",
      "colonia": "San Fernando (Pueblo Nuevo)",
      "postal_code": [
        "86650"
      ]
    },
    {
      "city": "Comalcalco",
      "colonia": "San Francisco",
      "postal_code": [
        "86330"
      ]
    },
    {
      "city": "Comalcalco",
      "colonia": "San Isidro",
      "postal_code": [
        "86357"
      ]
    },
    {
      "city": "Comalcalco",
      "colonia": "San Joaquin",
      "postal_code": [
        "86658"
      ]
    },
    {
      "city": "Comalcalco",
      "colonia": "San Miguel",
      "postal_code": [
        "86323"
      ]
    },
    {
      "city": "Comalcalco",
      "colonia": "San Silverio",
      "postal_code": [
        "86320"
      ]
    },
    {
      "city": "Comalcalco",
      "colonia": "Santa Amalia",
      "postal_code": [
        "86370"
      ]
    },
    {
      "city": "Comalcalco",
      "colonia": "Santo Domingo",
      "postal_code": [
        "86369"
      ]
    },
    {
      "city": "Comalcalco",
      "colonia": "Sargento Lopez 1ra. Seccion",
      "postal_code": [
        "86654"
      ]
    },
    {
      "city": "Comalcalco",
      "colonia": "Sargento Lopez 3ra. Seccion (San Jorge)",
      "postal_code": [
        "86654"
      ]
    },
    {
      "city": "Comalcalco",
      "colonia": "Sargento Lopez 4a Secc",
      "postal_code": [
        "86654"
      ]
    },
    {
      "city": "Comalcalco",
      "colonia": "Sgto. Lopez 2a Secc (El Chuzo)",
      "postal_code": [
        "86654"
      ]
    },
    {
      "city": "Comalcalco",
      "colonia": "Solidaridad Nacional A C",
      "postal_code": [
        "86340"
      ]
    },
    {
      "city": "Comalcalco",
      "colonia": "Sur 1ra. Seccion",
      "postal_code": [
        "86658"
      ]
    },
    {
      "city": "Comalcalco",
      "colonia": "Sur 2a Secc (La Trinidad)",
      "postal_code": [
        "86657"
      ]
    },
    {
      "city": "Comalcalco",
      "colonia": "Sur 3a Secc (El Zapote)",
      "postal_code": [
        "86657"
      ]
    },
    {
      "city": "Comalcalco",
      "colonia": "Sur 4ta. Seccion",
      "postal_code": [
        "86658"
      ]
    },
    {
      "city": "Comalcalco",
      "colonia": "Sur 5ta. Seccion",
      "postal_code": [
        "86658"
      ]
    },
    {
      "city": "Comalcalco",
      "colonia": "Sur Aldama",
      "postal_code": [
        "86640"
      ]
    },
    {
      "city": "Comalcalco",
      "colonia": "Tecolutilla",
      "postal_code": [
        "86640"
      ]
    },
    {
      "city": "Comalcalco",
      "colonia": "Tio Moncho (Urania Franyutti de Vazquez)",
      "postal_code": [
        "86644"
      ]
    },
    {
      "city": "Comalcalco",
      "colonia": "Tomas Garrido",
      "postal_code": [
        "86320"
      ]
    },
    {
      "city": "Comalcalco",
      "colonia": "Transito Tular",
      "postal_code": [
        "86643"
      ]
    },
    {
      "city": "Comalcalco",
      "colonia": "Uspi",
      "postal_code": [
        "86670"
      ]
    },
    {
      "city": "Comalcalco",
      "colonia": "Vicente Guerrero",
      "postal_code": [
        "86350"
      ]
    },
    {
      "city": "Comalcalco",
      "colonia": "Villa Maya",
      "postal_code": [
        "86324"
      ]
    },
    {
      "city": "Comalcalco",
      "colonia": "Villas de Oriente",
      "postal_code": [
        "86369"
      ]
    },
    {
      "city": "Comalcalco",
      "colonia": "Xochimilco",
      "postal_code": [
        "86369"
      ]
    },
    {
      "city": "Comalcalco",
      "colonia": "Zapotal 1ra. Seccion",
      "postal_code": [
        "86652"
      ]
    },
    {
      "city": "Comalcalco",
      "colonia": "Zapotal 2da. Seccion",
      "postal_code": [
        "86652"
      ]
    },
    {
      "city": "Comalcalco",
      "colonia": "Zapotal 3ra. Seccion",
      "postal_code": [
        "86652"
      ]
    }
  ]
}