{
  "data": [
    {
      "city": "Corregidora",
      "colonia": "1° de Mayo",
      "postal_code": [
        "76907"
      ]
    },
    {
      "city": "Corregidora",
      "colonia": "20 de Enero",
      "postal_code": [
        "76907"
      ]
    },
    {
      "city": "Corregidora",
      "colonia": "20 de Enero 2a Seccion",
      "postal_code": [
        "76907"
      ]
    },
    {
      "city": "Corregidora",
      "colonia": "21 de Marzo",
      "postal_code": [
        "76907"
      ]
    },
    {
      "city": "Corregidora",
      "colonia": "Acueducto Candiles",
      "postal_code": [
        "76902"
      ]
    },
    {
      "city": "Corregidora",
      "colonia": "Altos del Pueblito",
      "postal_code": [
        "76907"
      ]
    },
    {
      "city": "Corregidora",
      "colonia": "Amanecer Balvanera",
      "postal_code": [
        "76908"
      ]
    },
    {
      "city": "Corregidora",
      "colonia": "Ampliacion el Pueblito",
      "postal_code": [
        "76900"
      ]
    },
    {
      "city": "Corregidora",
      "colonia": "Ampliacion Huertas del Carmen",
      "postal_code": [
        "76904"
      ]
    },
    {
      "city": "Corregidora",
      "colonia": "Ampliacion los angeles",
      "postal_code": [
        "76908"
      ]
    },
    {
      "city": "Corregidora",
      "colonia": "Amstel I",
      "postal_code": [
        "76902"
      ]
    },
    {
      "city": "Corregidora",
      "colonia": "Amstel II",
      "postal_code": [
        "76902"
      ]
    },
    {
      "city": "Corregidora",
      "colonia": "Amstel IV",
      "postal_code": [
        "76902"
      ]
    },
    {
      "city": "Corregidora",
      "colonia": "Amstel V",
      "postal_code": [
        "76902"
      ]
    },
    {
      "city": "Corregidora",
      "colonia": "amsterdam",
      "postal_code": [
        "76902"
      ]
    },
    {
      "city": "Corregidora",
      "colonia": "Arroyo Hondo",
      "postal_code": [
        "76922"
      ]
    },
    {
      "city": "Corregidora",
      "colonia": "Azahar Residencial",
      "postal_code": [
        "76904"
      ]
    },
    {
      "city": "Corregidora",
      "colonia": "Bahamas",
      "postal_code": [
        "76905"
      ]
    },
    {
      "city": "Corregidora",
      "colonia": "Balcones de la Negreta",
      "postal_code": [
        "76907"
      ]
    },
    {
      "city": "Corregidora",
      "colonia": "Balcones de Vista Real",
      "postal_code": [
        "76905"
      ]
    },
    {
      "city": "Corregidora",
      "colonia": "Balvanera",
      "postal_code": [
        "76908"
      ]
    },
    {
      "city": "Corregidora",
      "colonia": "Balvanera Polo y Country Club",
      "postal_code": [
        "76915"
      ]
    },
    {
      "city": "Corregidora",
      "colonia": "Bernardo Quintana Arrioja",
      "postal_code": [
        "76903"
      ]
    },
    {
      "city": "Corregidora",
      "colonia": "Bosques de Lourdes",
      "postal_code": [
        "76927"
      ]
    },
    {
      "city": "Corregidora",
      "colonia": "Bosques de Viena",
      "postal_code": [
        "76905"
      ]
    },
    {
      "city": "Corregidora",
      "colonia": "Boulevares del Cimatario",
      "postal_code": [
        "76903"
      ]
    },
    {
      "city": "Corregidora",
      "colonia": "Bravo",
      "postal_code": [
        "76925"
      ]
    },
    {
      "city": "Corregidora",
      "colonia": "Camelinas",
      "postal_code": [
        "76903"
      ]
    },
    {
      "city": "Corregidora",
      "colonia": "Camino Real",
      "postal_code": [
        "76903"
      ]
    },
    {
      "city": "Corregidora",
      "colonia": "Canadas del Lago",
      "postal_code": [
        "76922"
      ]
    },
    {
      "city": "Corregidora",
      "colonia": "Carlota Hacienda Vanegas",
      "postal_code": [
        "76910"
      ]
    },
    {
      "city": "Corregidora",
      "colonia": "Casa Magna",
      "postal_code": [
        "76910"
      ]
    },
    {
      "city": "Corregidora",
      "colonia": "Catalina",
      "postal_code": [
        "76900"
      ]
    },
    {
      "city": "Corregidora",
      "colonia": "Charco Blanco",
      "postal_code": [
        "76926"
      ]
    },
    {
      "city": "Corregidora",
      "colonia": "Claustros del Campestre",
      "postal_code": [
        "76903"
      ]
    },
    {
      "city": "Corregidora",
      "colonia": "Colinas de Balvanera",
      "postal_code": [
        "76908"
      ]
    },
    {
      "city": "Corregidora",
      "colonia": "Colinas del Bosque 1a Seccion",
      "postal_code": [
        "76904"
      ]
    },
    {
      "city": "Corregidora",
      "colonia": "Colinas del Bosque 2a Seccion",
      "postal_code": [
        "76905"
      ]
    },
    {
      "city": "Corregidora",
      "colonia": "Colinas de los angeles",
      "postal_code": [
        "76908"
      ]
    },
    {
      "city": "Corregidora",
      "colonia": "Colinas del Remanso",
      "postal_code": [
        "76904"
      ]
    },
    {
      "city": "Corregidora",
      "colonia": "Colinas del Santuario",
      "postal_code": [
        "76904"
      ]
    },
    {
      "city": "Corregidora",
      "colonia": "Colinas del Sol",
      "postal_code": [
        "76903"
      ]
    },
    {
      "city": "Corregidora",
      "colonia": "Colinas del Sur",
      "postal_code": [
        "76903",
        "76907"
      ]
    },
    {
      "city": "Corregidora",
      "colonia": "Condes (Residencial)",
      "postal_code": [
        "76922"
      ]
    },
    {
      "city": "Corregidora",
      "colonia": "Cruz de Fuego",
      "postal_code": [
        "76912"
      ]
    },
    {
      "city": "Corregidora",
      "colonia": "Cumbres del Roble",
      "postal_code": [
        "76903"
      ]
    },
    {
      "city": "Corregidora",
      "colonia": "De la Saca",
      "postal_code": [
        "76904"
      ]
    },
    {
      "city": "Corregidora",
      "colonia": "Desarrollo Hidalgo (Desarrollo Zapata)",
      "postal_code": [
        "76910"
      ]
    },
    {
      "city": "Corregidora",
      "colonia": "Doctores",
      "postal_code": [
        "76927"
      ]
    },
    {
      "city": "Corregidora",
      "colonia": "Don Bosco",
      "postal_code": [
        "76900"
      ]
    },
    {
      "city": "Corregidora",
      "colonia": "El Batan",
      "postal_code": [
        "76902"
      ]
    },
    {
      "city": "Corregidora",
      "colonia": "El Calichar",
      "postal_code": [
        "76928"
      ]
    },
    {
      "city": "Corregidora",
      "colonia": "El Condado",
      "postal_code": [
        "76922"
      ]
    },
    {
      "city": "Corregidora",
      "colonia": "El Fortin",
      "postal_code": [
        "76902"
      ]
    },
    {
      "city": "Corregidora",
      "colonia": "El Jaral",
      "postal_code": [
        "76926"
      ]
    },
    {
      "city": "Corregidora",
      "colonia": "El Manantial",
      "postal_code": [
        "76922"
      ]
    },
    {
      "city": "Corregidora",
      "colonia": "El Milagrito",
      "postal_code": [
        "76907"
      ]
    },
    {
      "city": "Corregidora",
      "colonia": "El Paraiso",
      "postal_code": [
        "76905"
      ]
    },
    {
      "city": "Corregidora",
      "colonia": "El Pocito",
      "postal_code": [
        "76902"
      ]
    },
    {
      "city": "Corregidora",
      "colonia": "El Portico",
      "postal_code": [
        "76902"
      ]
    },
    {
      "city": "Corregidora",
      "colonia": "El Prado Residencial",
      "postal_code": [
        "76904"
      ]
    },
    {
      "city": "Corregidora",
      "colonia": "El Progreso (Las Trojas)",
      "postal_code": [
        "76922"
      ]
    },
    {
      "city": "Corregidora",
      "colonia": "El Pueblito",
      "postal_code": [
        "76904"
      ]
    },
    {
      "city": "Corregidora",
      "colonia": "El Pueblito Centro",
      "postal_code": [
        "76900"
      ]
    },
    {
      "city": "Corregidora",
      "colonia": "El Ranchito",
      "postal_code": [
        "76923"
      ]
    },
    {
      "city": "Corregidora",
      "colonia": "El Risco Residencial",
      "postal_code": [
        "76903"
      ]
    },
    {
      "city": "Corregidora",
      "colonia": "El Roble",
      "postal_code": [
        "76902"
      ]
    },
    {
      "city": "Corregidora",
      "colonia": "El Rocio Residencial",
      "postal_code": [
        "76900"
      ]
    },
    {
      "city": "Corregidora",
      "colonia": "El Romeral",
      "postal_code": [
        "76915"
      ]
    },
    {
      "city": "Corregidora",
      "colonia": "El Sabino",
      "postal_code": [
        "76922"
      ]
    },
    {
      "city": "Corregidora",
      "colonia": "El Sorgo",
      "postal_code": [
        "76900"
      ]
    },
    {
      "city": "Corregidora",
      "colonia": "El Zorzal",
      "postal_code": [
        "76900"
      ]
    },
    {
      "city": "Corregidora",
      "colonia": "Emiliano Zapata",
      "postal_code": [
        "76900"
      ]
    },
    {
      "city": "Corregidora",
      "colonia": "Espiritu Santo",
      "postal_code": [
        "76907"
      ]
    },
    {
      "city": "Corregidora",
      "colonia": "Federal del Rio",
      "postal_code": [
        "76908"
      ]
    },
    {
      "city": "Corregidora",
      "colonia": "Filosofal",
      "postal_code": [
        "76904"
      ]
    },
    {
      "city": "Corregidora",
      "colonia": "Fraccion San Luis",
      "postal_code": [
        "76925"
      ]
    },
    {
      "city": "Corregidora",
      "colonia": "Francisco Villa",
      "postal_code": [
        "76903"
      ]
    },
    {
      "city": "Corregidora",
      "colonia": "Gallegos",
      "postal_code": [
        "76900"
      ]
    },
    {
      "city": "Corregidora",
      "colonia": "Hacienda el Batan",
      "postal_code": [
        "76920"
      ]
    },
    {
      "city": "Corregidora",
      "colonia": "Hacienda Real Tejeda",
      "postal_code": [
        "76904"
      ]
    },
    {
      "city": "Corregidora",
      "colonia": "Hacienda San Gabriel",
      "postal_code": [
        "76904"
      ]
    },
    {
      "city": "Corregidora",
      "colonia": "Haciendas del Pueblito",
      "postal_code": [
        "76900"
      ]
    },
    {
      "city": "Corregidora",
      "colonia": "Huertas de la Virgen",
      "postal_code": [
        "76900"
      ]
    },
    {
      "city": "Corregidora",
      "colonia": "Huertas el Carmen",
      "postal_code": [
        "76904"
      ]
    },
    {
      "city": "Corregidora",
      "colonia": "Jardines de la Corregidora",
      "postal_code": [
        "76910"
      ]
    },
    {
      "city": "Corregidora",
      "colonia": "Jardines de la Negreta",
      "postal_code": [
        "76907"
      ]
    },
    {
      "city": "Corregidora",
      "colonia": "Jose Maria Truchuelo",
      "postal_code": [
        "76903"
      ]
    },
    {
      "city": "Corregidora",
      "colonia": "La Antigua",
      "postal_code": [
        "76900"
      ]
    },
    {
      "city": "Corregidora",
      "colonia": "La Cantera",
      "postal_code": [
        "76926"
      ]
    },
    {
      "city": "Corregidora",
      "colonia": "La Cienega",
      "postal_code": [
        "76900"
      ]
    },
    {
      "city": "Corregidora",
      "colonia": "La Cueva",
      "postal_code": [
        "76926"
      ]
    },
    {
      "city": "Corregidora",
      "colonia": "La Gavia",
      "postal_code": [
        "76904"
      ]
    },
    {
      "city": "Corregidora",
      "colonia": "La Hacienda",
      "postal_code": [
        "76904"
      ]
    },
    {
      "city": "Corregidora",
      "colonia": "La Negreta",
      "postal_code": [
        "76907"
      ]
    },
    {
      "city": "Corregidora",
      "colonia": "La Palma",
      "postal_code": [
        "76908"
      ]
    },
    {
      "city": "Corregidora",
      "colonia": "La Piramide",
      "postal_code": [
        "76900"
      ]
    },
    {
      "city": "Corregidora",
      "colonia": "La Poza",
      "postal_code": [
        "76923"
      ]
    },
    {
      "city": "Corregidora",
      "colonia": "La Purisima de la Cueva",
      "postal_code": [
        "76926"
      ]
    },
    {
      "city": "Corregidora",
      "colonia": "Las Cabanas",
      "postal_code": [
        "76908"
      ]
    },
    {
      "city": "Corregidora",
      "colonia": "Las Delicias",
      "postal_code": [
        "76902"
      ]
    },
    {
      "city": "Corregidora",
      "colonia": "Las Flores",
      "postal_code": [
        "76900",
        "76900"
      ]
    },
    {
      "city": "Corregidora",
      "colonia": "Las Fuentes",
      "postal_code": [
        "76904"
      ]
    },
    {
      "city": "Corregidora",
      "colonia": "Las Palomas",
      "postal_code": [
        "76900"
      ]
    },
    {
      "city": "Corregidora",
      "colonia": "Las Taponas",
      "postal_code": [
        "76925"
      ]
    },
    {
      "city": "Corregidora",
      "colonia": "La Tinaja",
      "postal_code": [
        "76923"
      ]
    },
    {
      "city": "Corregidora",
      "colonia": "Loma Bonita",
      "postal_code": [
        "76926"
      ]
    },
    {
      "city": "Corregidora",
      "colonia": "Loma de San Isidro",
      "postal_code": [
        "76924"
      ]
    },
    {
      "city": "Corregidora",
      "colonia": "Lomas de Balvanera",
      "postal_code": [
        "76908"
      ]
    },
    {
      "city": "Corregidora",
      "colonia": "Lomas de Charco Blanco",
      "postal_code": [
        "76926"
      ]
    },
    {
      "city": "Corregidora",
      "colonia": "Lomas de la Cruz",
      "postal_code": [
        "76907"
      ]
    },
    {
      "city": "Corregidora",
      "colonia": "Lomas del Campestre",
      "postal_code": [
        "76903"
      ]
    },
    {
      "city": "Corregidora",
      "colonia": "Lomas del Mirador",
      "postal_code": [
        "76903"
      ]
    },
    {
      "city": "Corregidora",
      "colonia": "Lomas del Sur",
      "postal_code": [
        "76905"
      ]
    },
    {
      "city": "Corregidora",
      "colonia": "Lomas de Zaragoza",
      "postal_code": [
        "76920"
      ]
    },
    {
      "city": "Corregidora",
      "colonia": "Loretto Residencial",
      "postal_code": [
        "76927"
      ]
    },
    {
      "city": "Corregidora",
      "colonia": "Los angeles",
      "postal_code": [
        "76908"
      ]
    },
    {
      "city": "Corregidora",
      "colonia": "Los Arrayanes",
      "postal_code": [
        "76908"
      ]
    },
    {
      "city": "Corregidora",
      "colonia": "Los Candiles",
      "postal_code": [
        "76903"
      ]
    },
    {
      "city": "Corregidora",
      "colonia": "Los Cipreses",
      "postal_code": [
        "76905"
      ]
    },
    {
      "city": "Corregidora",
      "colonia": "Los Frailes",
      "postal_code": [
        "76900"
      ]
    },
    {
      "city": "Corregidora",
      "colonia": "Los Mendoza",
      "postal_code": [
        "76904"
      ]
    },
    {
      "city": "Corregidora",
      "colonia": "Los Mezquites",
      "postal_code": [
        "76912"
      ]
    },
    {
      "city": "Corregidora",
      "colonia": "Los Nogales",
      "postal_code": [
        "76900"
      ]
    },
    {
      "city": "Corregidora",
      "colonia": "Los Olivos",
      "postal_code": [
        "76903"
      ]
    },
    {
      "city": "Corregidora",
      "colonia": "Los Olvera",
      "postal_code": [
        "76904"
      ]
    },
    {
      "city": "Corregidora",
      "colonia": "Los Pajaros",
      "postal_code": [
        "76904"
      ]
    },
    {
      "city": "Corregidora",
      "colonia": "Los Pinos",
      "postal_code": [
        "76902"
      ]
    },
    {
      "city": "Corregidora",
      "colonia": "Los Reyes",
      "postal_code": [
        "76907"
      ]
    },
    {
      "city": "Corregidora",
      "colonia": "Lourdes",
      "postal_code": [
        "76927"
      ]
    },
    {
      "city": "Corregidora",
      "colonia": "Luis Donaldo Colosio",
      "postal_code": [
        "76907"
      ]
    },
    {
      "city": "Corregidora",
      "colonia": "Luz Maria",
      "postal_code": [
        "76904"
      ]
    },
    {
      "city": "Corregidora",
      "colonia": "Magisterial",
      "postal_code": [
        "76912"
      ]
    },
    {
      "city": "Corregidora",
      "colonia": "Maravillas",
      "postal_code": [
        "76904"
      ]
    },
    {
      "city": "Corregidora",
      "colonia": "Mediterraneo I",
      "postal_code": [
        "76908"
      ]
    },
    {
      "city": "Corregidora",
      "colonia": "Mediterraneo II",
      "postal_code": [
        "76908"
      ]
    },
    {
      "city": "Corregidora",
      "colonia": "Mediterraneo III",
      "postal_code": [
        "76908"
      ]
    },
    {
      "city": "Corregidora",
      "colonia": "Mision Antigua",
      "postal_code": [
        "76904"
      ]
    },
    {
      "city": "Corregidora",
      "colonia": "Mision Candiles",
      "postal_code": [
        "76903"
      ]
    },
    {
      "city": "Corregidora",
      "colonia": "Mision de San Carlos",
      "postal_code": [
        "76903"
      ]
    },
    {
      "city": "Corregidora",
      "colonia": "Mision de Santa Sofia",
      "postal_code": [
        "76902"
      ]
    },
    {
      "city": "Corregidora",
      "colonia": "Mision de Santiago",
      "postal_code": [
        "76902"
      ]
    },
    {
      "city": "Corregidora",
      "colonia": "Misiones de Corregidora",
      "postal_code": [
        "76900"
      ]
    },
    {
      "city": "Corregidora",
      "colonia": "Mision la Esperanza",
      "postal_code": [
        "76900"
      ]
    },
    {
      "city": "Corregidora",
      "colonia": "Mision Marbella",
      "postal_code": [
        "76904"
      ]
    },
    {
      "city": "Corregidora",
      "colonia": "Mision Mariana",
      "postal_code": [
        "76903"
      ]
    },
    {
      "city": "Corregidora",
      "colonia": "Mision Regina",
      "postal_code": [
        "76907"
      ]
    },
    {
      "city": "Corregidora",
      "colonia": "Mision San Joaquin",
      "postal_code": [
        "76904"
      ]
    },
    {
      "city": "Corregidora",
      "colonia": "Mision San Jose",
      "postal_code": [
        "76907"
      ]
    },
    {
      "city": "Corregidora",
      "colonia": "Mision San Juan",
      "postal_code": [
        "76907"
      ]
    },
    {
      "city": "Corregidora",
      "colonia": "Moralta Residencial",
      "postal_code": [
        "76908"
      ]
    },
    {
      "city": "Corregidora",
      "colonia": "Ninos Heroes de Chapultepec",
      "postal_code": [
        "76908"
      ]
    },
    {
      "city": "Corregidora",
      "colonia": "Orquideas",
      "postal_code": [
        "76900"
      ]
    },
    {
      "city": "Corregidora",
      "colonia": "Paisajes de Lourdes",
      "postal_code": [
        "76927"
      ]
    },
    {
      "city": "Corregidora",
      "colonia": "Panorama",
      "postal_code": [
        "76904"
      ]
    },
    {
      "city": "Corregidora",
      "colonia": "Paseos del Bosque",
      "postal_code": [
        "76910"
      ]
    },
    {
      "city": "Corregidora",
      "colonia": "Pedregal de Schoenstatt",
      "postal_code": [
        "76904",
        "76904"
      ]
    },
    {
      "city": "Corregidora",
      "colonia": "Piramides",
      "postal_code": [
        "76908"
      ]
    },
    {
      "city": "Corregidora",
      "colonia": "Piramides 3a. Seccion",
      "postal_code": [
        "76908"
      ]
    },
    {
      "city": "Corregidora",
      "colonia": "Pirules",
      "postal_code": [
        "76904"
      ]
    },
    {
      "city": "Corregidora",
      "colonia": "Pita",
      "postal_code": [
        "76926"
      ]
    },
    {
      "city": "Corregidora",
      "colonia": "Popular Ecologica Valle de Oro",
      "postal_code": [
        "76905"
      ]
    },
    {
      "city": "Corregidora",
      "colonia": "Portal del angel",
      "postal_code": [
        "76900"
      ]
    },
    {
      "city": "Corregidora",
      "colonia": "Praderas del Bosque",
      "postal_code": [
        "76905"
      ]
    },
    {
      "city": "Corregidora",
      "colonia": "Praderas de los angeles",
      "postal_code": [
        "76908"
      ]
    },
    {
      "city": "Corregidora",
      "colonia": "Praderas de Lourdes",
      "postal_code": [
        "76927"
      ]
    },
    {
      "city": "Corregidora",
      "colonia": "Prados de Balvanera",
      "postal_code": [
        "76907"
      ]
    },
    {
      "city": "Corregidora",
      "colonia": "Presa de Bravo",
      "postal_code": [
        "76924"
      ]
    },
    {
      "city": "Corregidora",
      "colonia": "Privada Bellavista",
      "postal_code": [
        "76900"
      ]
    },
    {
      "city": "Corregidora",
      "colonia": "Privada Campestre",
      "postal_code": [
        "76902"
      ]
    },
    {
      "city": "Corregidora",
      "colonia": "Privada de las Capillas",
      "postal_code": [
        "76900"
      ]
    },
    {
      "city": "Corregidora",
      "colonia": "Privada las Mariposas",
      "postal_code": [
        "76904"
      ]
    },
    {
      "city": "Corregidora",
      "colonia": "Pueblito Colonial",
      "postal_code": [
        "76908"
      ]
    },
    {
      "city": "Corregidora",
      "colonia": "Pueblo Nuevo",
      "postal_code": [
        "76900"
      ]
    },
    {
      "city": "Corregidora",
      "colonia": "Puerta de Piedra",
      "postal_code": [
        "76908"
      ]
    },
    {
      "city": "Corregidora",
      "colonia": "Puerta de San Rafael",
      "postal_code": [
        "76924"
      ]
    },
    {
      "city": "Corregidora",
      "colonia": "Puerta Real",
      "postal_code": [
        "76910"
      ]
    },
    {
      "city": "Corregidora",
      "colonia": "Punta Esmeralda",
      "postal_code": [
        "76906"
      ]
    },
    {
      "city": "Corregidora",
      "colonia": "Purisima de San Rafael",
      "postal_code": [
        "76923"
      ]
    },
    {
      "city": "Corregidora",
      "colonia": "Quintas del Bosque",
      "postal_code": [
        "76900"
      ]
    },
    {
      "city": "Corregidora",
      "colonia": "Real del Bosque",
      "postal_code": [
        "76922"
      ]
    },
    {
      "city": "Corregidora",
      "colonia": "Residencial Andrea",
      "postal_code": [
        "76903"
      ]
    },
    {
      "city": "Corregidora",
      "colonia": "Residencial Bellavista Diamante",
      "postal_code": [
        "76900"
      ]
    },
    {
      "city": "Corregidora",
      "colonia": "Residencial Bellavista Mezquites",
      "postal_code": [
        "76900"
      ]
    },
    {
      "city": "Corregidora",
      "colonia": "Residencial las Trojes",
      "postal_code": [
        "76908"
      ]
    },
    {
      "city": "Corregidora",
      "colonia": "Residencial la Vista",
      "postal_code": [
        "76904"
      ]
    },
    {
      "city": "Corregidora",
      "colonia": "Residencial los Vitrales",
      "postal_code": [
        "76904"
      ]
    },
    {
      "city": "Corregidora",
      "colonia": "Residencial Santa Fe",
      "postal_code": [
        "76930"
      ]
    },
    {
      "city": "Corregidora",
      "colonia": "Rinconada Campestre",
      "postal_code": [
        "76903"
      ]
    },
    {
      "city": "Corregidora",
      "colonia": "Rinconada de la Virgen",
      "postal_code": [
        "76900"
      ]
    },
    {
      "city": "Corregidora",
      "colonia": "Rinconada Mediterraneo",
      "postal_code": [
        "76908"
      ]
    },
    {
      "city": "Corregidora",
      "colonia": "Rincon Campestre",
      "postal_code": [
        "76902"
      ]
    },
    {
      "city": "Corregidora",
      "colonia": "Rincon Colonial",
      "postal_code": [
        "76900"
      ]
    },
    {
      "city": "Corregidora",
      "colonia": "Rincon de Guadalupe",
      "postal_code": [
        "76907"
      ]
    },
    {
      "city": "Corregidora",
      "colonia": "San Agustin",
      "postal_code": [
        "76905"
      ]
    },
    {
      "city": "Corregidora",
      "colonia": "San Felipe Calichar",
      "postal_code": [
        "76928"
      ]
    },
    {
      "city": "Corregidora",
      "colonia": "San Francisco",
      "postal_code": [
        "76922"
      ]
    },
    {
      "city": "Corregidora",
      "colonia": "San Jeronimo",
      "postal_code": [
        "76910"
      ]
    },
    {
      "city": "Corregidora",
      "colonia": "San Jose de los Olvera",
      "postal_code": [
        "76902"
      ]
    },
    {
      "city": "Corregidora",
      "colonia": "San Juanico",
      "postal_code": [
        "76930"
      ]
    },
    {
      "city": "Corregidora",
      "colonia": "San Mateo",
      "postal_code": [
        "76912"
      ]
    },
    {
      "city": "Corregidora",
      "colonia": "San Miguelito",
      "postal_code": [
        "76900",
        "76924"
      ]
    },
    {
      "city": "Corregidora",
      "colonia": "San Rafael",
      "postal_code": [
        "76924"
      ]
    },
    {
      "city": "Corregidora",
      "colonia": "Santa Barbara 1a Seccion",
      "postal_code": [
        "76906"
      ]
    },
    {
      "city": "Corregidora",
      "colonia": "Santa Barbara 2a Seccion",
      "postal_code": [
        "76906"
      ]
    },
    {
      "city": "Corregidora",
      "colonia": "Santa Lucia",
      "postal_code": [
        "76902"
      ]
    },
    {
      "city": "Corregidora",
      "colonia": "Santa Maria Magdalena",
      "postal_code": [
        "76930"
      ]
    },
    {
      "city": "Corregidora",
      "colonia": "Santa Virginia",
      "postal_code": [
        "76908"
      ]
    },
    {
      "city": "Corregidora",
      "colonia": "Santuarios del Cerrito",
      "postal_code": [
        "76900"
      ]
    },
    {
      "city": "Corregidora",
      "colonia": "Tabachines",
      "postal_code": [
        "76902"
      ]
    },
    {
      "city": "Corregidora",
      "colonia": "Talavera",
      "postal_code": [
        "76900"
      ]
    },
    {
      "city": "Corregidora",
      "colonia": "Tejeda",
      "postal_code": [
        "76904"
      ]
    },
    {
      "city": "Corregidora",
      "colonia": "Terranova",
      "postal_code": [
        "76910"
      ]
    },
    {
      "city": "Corregidora",
      "colonia": "Tierra y Libertad",
      "postal_code": [
        "76903"
      ]
    },
    {
      "city": "Corregidora",
      "colonia": "Trojitas",
      "postal_code": [
        "76908"
      ]
    },
    {
      "city": "Corregidora",
      "colonia": "Valle Arboledas",
      "postal_code": [
        "76907"
      ]
    },
    {
      "city": "Corregidora",
      "colonia": "Valle de Aragon 1a Seccion",
      "postal_code": [
        "76907"
      ]
    },
    {
      "city": "Corregidora",
      "colonia": "Valle de los Olivos",
      "postal_code": [
        "76902"
      ]
    },
    {
      "city": "Corregidora",
      "colonia": "Valle de los Pinos",
      "postal_code": [
        "76907"
      ]
    },
    {
      "city": "Corregidora",
      "colonia": "Valle de Santiago",
      "postal_code": [
        "76907"
      ]
    },
    {
      "city": "Corregidora",
      "colonia": "Valle Diamante",
      "postal_code": [
        "76903"
      ]
    },
    {
      "city": "Corregidora",
      "colonia": "Valle Dorado 2000",
      "postal_code": [
        "76908"
      ]
    },
    {
      "city": "Corregidora",
      "colonia": "Valle Real Residencial",
      "postal_code": [
        "76903"
      ]
    },
    {
      "city": "Corregidora",
      "colonia": "Venceremos",
      "postal_code": [
        "76903"
      ]
    },
    {
      "city": "Corregidora",
      "colonia": "Veredas",
      "postal_code": [
        "76930"
      ]
    },
    {
      "city": "Corregidora",
      "colonia": "Villa Antigua",
      "postal_code": [
        "76900"
      ]
    },
    {
      "city": "Corregidora",
      "colonia": "Villas Campestre",
      "postal_code": [
        "76902"
      ]
    },
    {
      "city": "Corregidora",
      "colonia": "Villas Campestre 2a. Seccion",
      "postal_code": [
        "76902"
      ]
    },
    {
      "city": "Corregidora",
      "colonia": "Villas de la Corregidora",
      "postal_code": [
        "76900"
      ]
    },
    {
      "city": "Corregidora",
      "colonia": "Villas de las Flores",
      "postal_code": [
        "76907"
      ]
    },
    {
      "city": "Corregidora",
      "colonia": "Villas de Tejeda",
      "postal_code": [
        "76902"
      ]
    },
    {
      "city": "Corregidora",
      "colonia": "Villas Fontana",
      "postal_code": [
        "76903"
      ]
    },
    {
      "city": "Corregidora",
      "colonia": "Vista Hermosa",
      "postal_code": [
        "76905"
      ]
    },
    {
      "city": "Corregidora",
      "colonia": "Vista Real y Country Club",
      "postal_code": [
        "76905"
      ]
    },
    {
      "city": "Corregidora",
      "colonia": "Vistas del Campestre",
      "postal_code": [
        "76903"
      ]
    },
    {
      "city": "Corregidora",
      "colonia": "Vistas del Sol",
      "postal_code": [
        "76927"
      ]
    }
  ]
}