{
  "data": [
    {
      "city": "Kanasin",
      "colonia": "alamos de Oriente",
      "postal_code": [
        "97370"
      ]
    },
    {
      "city": "Kanasin",
      "colonia": "Alamos Mulchechen",
      "postal_code": [
        "97370"
      ]
    },
    {
      "city": "Kanasin",
      "colonia": "Amalia Solorzano II",
      "postal_code": [
        "97370"
      ]
    },
    {
      "city": "Kanasin",
      "colonia": "Ampliacion Xelpac",
      "postal_code": [
        "97370"
      ]
    },
    {
      "city": "Kanasin",
      "colonia": "Andres Quintana Roo",
      "postal_code": [
        "97370"
      ]
    },
    {
      "city": "Kanasin",
      "colonia": "Arboleda Kanasin",
      "postal_code": [
        "97370"
      ]
    },
    {
      "city": "Kanasin",
      "colonia": "Arecas",
      "postal_code": [
        "97370"
      ]
    },
    {
      "city": "Kanasin",
      "colonia": "Cecilio Chi",
      "postal_code": [
        "97370"
      ]
    },
    {
      "city": "Kanasin",
      "colonia": "Cielo Alto",
      "postal_code": [
        "97370"
      ]
    },
    {
      "city": "Kanasin",
      "colonia": "Colibri",
      "postal_code": [
        "97370"
      ]
    },
    {
      "city": "Kanasin",
      "colonia": "Condesa",
      "postal_code": [
        "97370"
      ]
    },
    {
      "city": "Kanasin",
      "colonia": "Coyoles",
      "postal_code": [
        "97370"
      ]
    },
    {
      "city": "Kanasin",
      "colonia": "CROC",
      "postal_code": [
        "97370"
      ]
    },
    {
      "city": "Kanasin",
      "colonia": "Cuauhtemoc",
      "postal_code": [
        "97370"
      ]
    },
    {
      "city": "Kanasin",
      "colonia": "Despertare",
      "postal_code": [
        "97370"
      ]
    },
    {
      "city": "Kanasin",
      "colonia": "El Cerrito",
      "postal_code": [
        "97370"
      ]
    },
    {
      "city": "Kanasin",
      "colonia": "El Encanto Kanasin",
      "postal_code": [
        "97370"
      ]
    },
    {
      "city": "Kanasin",
      "colonia": "Flor de Mayo",
      "postal_code": [
        "97370"
      ]
    },
    {
      "city": "Kanasin",
      "colonia": "Fontana I",
      "postal_code": [
        "97370"
      ]
    },
    {
      "city": "Kanasin",
      "colonia": "Francisco Villa Oriente",
      "postal_code": [
        "97370"
      ]
    },
    {
      "city": "Kanasin",
      "colonia": "Girasoles",
      "postal_code": [
        "97370"
      ]
    },
    {
      "city": "Kanasin",
      "colonia": "Hector Victoria",
      "postal_code": [
        "97370"
      ]
    },
    {
      "city": "Kanasin",
      "colonia": "Jardines de Kanasin",
      "postal_code": [
        "97370"
      ]
    },
    {
      "city": "Kanasin",
      "colonia": "Jardines de Mulchechen",
      "postal_code": [
        "97370"
      ]
    },
    {
      "city": "Kanasin",
      "colonia": "Jardines de San Pedro Noh Pat",
      "postal_code": [
        "97370"
      ]
    },
    {
      "city": "Kanasin",
      "colonia": "Kanasin Centro",
      "postal_code": [
        "97370"
      ]
    },
    {
      "city": "Kanasin",
      "colonia": "La Ceiba",
      "postal_code": [
        "97370"
      ]
    },
    {
      "city": "Kanasin",
      "colonia": "La Joya",
      "postal_code": [
        "97370"
      ]
    },
    {
      "city": "Kanasin",
      "colonia": "La Piedra",
      "postal_code": [
        "97370"
      ]
    },
    {
      "city": "Kanasin",
      "colonia": "Las Flores",
      "postal_code": [
        "97370"
      ]
    },
    {
      "city": "Kanasin",
      "colonia": "Las Haciendas",
      "postal_code": [
        "97370"
      ]
    },
    {
      "city": "Kanasin",
      "colonia": "Las Palmas Yucatan",
      "postal_code": [
        "97370"
      ]
    },
    {
      "city": "Kanasin",
      "colonia": "Las Palmeras",
      "postal_code": [
        "97370"
      ]
    },
    {
      "city": "Kanasin",
      "colonia": "Las Perlas",
      "postal_code": [
        "97370"
      ]
    },
    {
      "city": "Kanasin",
      "colonia": "Leona Vicario",
      "postal_code": [
        "97370"
      ]
    },
    {
      "city": "Kanasin",
      "colonia": "Los Encinos",
      "postal_code": [
        "97370"
      ]
    },
    {
      "city": "Kanasin",
      "colonia": "Los Pinos de Mulchechen",
      "postal_code": [
        "97370"
      ]
    },
    {
      "city": "Kanasin",
      "colonia": "Los Robles",
      "postal_code": [
        "97370"
      ]
    },
    {
      "city": "Kanasin",
      "colonia": "Los Robles III",
      "postal_code": [
        "97370"
      ]
    },
    {
      "city": "Kanasin",
      "colonia": "Los Tulipanes",
      "postal_code": [
        "97370"
      ]
    },
    {
      "city": "Kanasin",
      "colonia": "Mulchechen",
      "postal_code": [
        "97370"
      ]
    },
    {
      "city": "Kanasin",
      "colonia": "Mulchechen II",
      "postal_code": [
        "97370"
      ]
    },
    {
      "city": "Kanasin",
      "colonia": "Pablo Moreno",
      "postal_code": [
        "97370"
      ]
    },
    {
      "city": "Kanasin",
      "colonia": "Palmas San Pedro",
      "postal_code": [
        "97370"
      ]
    },
    {
      "city": "Kanasin",
      "colonia": "Pedregales de Kanasin",
      "postal_code": [
        "97370"
      ]
    },
    {
      "city": "Kanasin",
      "colonia": "Pedregales de Kanasin II",
      "postal_code": [
        "97370"
      ]
    },
    {
      "city": "Kanasin",
      "colonia": "Pedregales del Oriente",
      "postal_code": [
        "97370"
      ]
    },
    {
      "city": "Kanasin",
      "colonia": "Privada del Sol",
      "postal_code": [
        "97370"
      ]
    },
    {
      "city": "Kanasin",
      "colonia": "Puerta del Sol",
      "postal_code": [
        "97370"
      ]
    },
    {
      "city": "Kanasin",
      "colonia": "Puerta Esmeralda",
      "postal_code": [
        "97370"
      ]
    },
    {
      "city": "Kanasin",
      "colonia": "Reparto las Granjas",
      "postal_code": [
        "97370"
      ]
    },
    {
      "city": "Kanasin",
      "colonia": "Residencial",
      "postal_code": [
        "97370"
      ]
    },
    {
      "city": "Kanasin",
      "colonia": "Rinconada Kanasin",
      "postal_code": [
        "97370"
      ]
    },
    {
      "city": "Kanasin",
      "colonia": "San Antonio Kaua III",
      "postal_code": [
        "97370"
      ]
    },
    {
      "city": "Kanasin",
      "colonia": "San Antonio Tehuitz",
      "postal_code": [
        "97376"
      ]
    },
    {
      "city": "Kanasin",
      "colonia": "San Aroldo",
      "postal_code": [
        "97374"
      ]
    },
    {
      "city": "Kanasin",
      "colonia": "San Camilo",
      "postal_code": [
        "97370"
      ]
    },
    {
      "city": "Kanasin",
      "colonia": "San Haroldo San Jose Tzal",
      "postal_code": [
        "97370"
      ]
    },
    {
      "city": "Kanasin",
      "colonia": "San Ignacio",
      "postal_code": [
        "97370"
      ]
    },
    {
      "city": "Kanasin",
      "colonia": "San Jose Kanasin",
      "postal_code": [
        "97370"
      ]
    },
    {
      "city": "Kanasin",
      "colonia": "San Pedro (Deshuesadero)",
      "postal_code": [
        "97374"
      ]
    },
    {
      "city": "Kanasin",
      "colonia": "San Pedro Noh Pat",
      "postal_code": [
        "97370"
      ]
    },
    {
      "city": "Kanasin",
      "colonia": "Santa Ana",
      "postal_code": [
        "97370"
      ]
    },
    {
      "city": "Kanasin",
      "colonia": "Santa Cecilia",
      "postal_code": [
        "97370"
      ]
    },
    {
      "city": "Kanasin",
      "colonia": "Santa Isabel",
      "postal_code": [
        "97373"
      ]
    },
    {
      "city": "Kanasin",
      "colonia": "Teya",
      "postal_code": [
        "97374"
      ]
    },
    {
      "city": "Kanasin",
      "colonia": "Valle Azul",
      "postal_code": [
        "97370"
      ]
    },
    {
      "city": "Kanasin",
      "colonia": "Valle Oriente",
      "postal_code": [
        "97370"
      ]
    },
    {
      "city": "Kanasin",
      "colonia": "Valle Oriente de San Pedro Noh Pat",
      "postal_code": [
        "97370"
      ]
    },
    {
      "city": "Kanasin",
      "colonia": "Villa Bonita",
      "postal_code": [
        "97370"
      ]
    },
    {
      "city": "Kanasin",
      "colonia": "Villa Mercedes",
      "postal_code": [
        "97370"
      ]
    },
    {
      "city": "Kanasin",
      "colonia": "Villas del Oriente",
      "postal_code": [
        "97370"
      ]
    },
    {
      "city": "Kanasin",
      "colonia": "Villas Turquesa",
      "postal_code": [
        "97370"
      ]
    },
    {
      "city": "Kanasin",
      "colonia": "VIVAH",
      "postal_code": [
        "97370"
      ]
    },
    {
      "city": "Kanasin",
      "colonia": "Xelpac",
      "postal_code": [
        "97370"
      ]
    }
  ]
}