{
  "data": [
    {
      "city": "Miguel Aleman",
      "colonia": "Adolfo Lopez Mateos",
      "postal_code": [
        "88305"
      ]
    },
    {
      "city": "Miguel Aleman",
      "colonia": "Arcabuz",
      "postal_code": [
        "88340"
      ]
    },
    {
      "city": "Miguel Aleman",
      "colonia": "Arguello",
      "postal_code": [
        "88305"
      ]
    },
    {
      "city": "Miguel Aleman",
      "colonia": "Barrera",
      "postal_code": [
        "88303"
      ]
    },
    {
      "city": "Miguel Aleman",
      "colonia": "Benito Juarez",
      "postal_code": [
        "88307"
      ]
    },
    {
      "city": "Miguel Aleman",
      "colonia": "Buenos Aires",
      "postal_code": [
        "88305"
      ]
    },
    {
      "city": "Miguel Aleman",
      "colonia": "Ciudad Miguel Aleman Centro",
      "postal_code": [
        "88300"
      ]
    },
    {
      "city": "Miguel Aleman",
      "colonia": "Cristobal Colon",
      "postal_code": [
        "88303"
      ]
    },
    {
      "city": "Miguel Aleman",
      "colonia": "Del Norte",
      "postal_code": [
        "88302"
      ]
    },
    {
      "city": "Miguel Aleman",
      "colonia": "Educacion",
      "postal_code": [
        "88306"
      ]
    },
    {
      "city": "Miguel Aleman",
      "colonia": "Electricistas",
      "postal_code": [
        "88306"
      ]
    },
    {
      "city": "Miguel Aleman",
      "colonia": "El Mirador",
      "postal_code": [
        "88304"
      ]
    },
    {
      "city": "Miguel Aleman",
      "colonia": "El Ranchito (Cerro Azul)",
      "postal_code": [
        "88349"
      ]
    },
    {
      "city": "Miguel Aleman",
      "colonia": "Gomez",
      "postal_code": [
        "88302"
      ]
    },
    {
      "city": "Miguel Aleman",
      "colonia": "Guadalupe",
      "postal_code": [
        "88304"
      ]
    },
    {
      "city": "Miguel Aleman",
      "colonia": "Guardados de Arriba",
      "postal_code": [
        "88321"
      ]
    },
    {
      "city": "Miguel Aleman",
      "colonia": "Hercilia",
      "postal_code": [
        "88306"
      ]
    },
    {
      "city": "Miguel Aleman",
      "colonia": "Independencia",
      "postal_code": [
        "88303"
      ]
    },
    {
      "city": "Miguel Aleman",
      "colonia": "INFONAVIT Arboleda",
      "postal_code": [
        "88302"
      ]
    },
    {
      "city": "Miguel Aleman",
      "colonia": "INFONAVIT Industrial",
      "postal_code": [
        "88306"
      ]
    },
    {
      "city": "Miguel Aleman",
      "colonia": "INFONAVIT Rinconada",
      "postal_code": [
        "88306"
      ]
    },
    {
      "city": "Miguel Aleman",
      "colonia": "INFONAVIT Santa Luisa",
      "postal_code": [
        "88306"
      ]
    },
    {
      "city": "Miguel Aleman",
      "colonia": "ITAVU",
      "postal_code": [
        "88307"
      ]
    },
    {
      "city": "Miguel Aleman",
      "colonia": "Jardin",
      "postal_code": [
        "88302"
      ]
    },
    {
      "city": "Miguel Aleman",
      "colonia": "Jardines de San German",
      "postal_code": [
        "88307"
      ]
    },
    {
      "city": "Miguel Aleman",
      "colonia": "La Ceja",
      "postal_code": [
        "88336"
      ]
    },
    {
      "city": "Miguel Aleman",
      "colonia": "Lindavista",
      "postal_code": [
        "88305"
      ]
    },
    {
      "city": "Miguel Aleman",
      "colonia": "Los angeles",
      "postal_code": [
        "88321"
      ]
    },
    {
      "city": "Miguel Aleman",
      "colonia": "Los Guajillos",
      "postal_code": [
        "88330"
      ]
    },
    {
      "city": "Miguel Aleman",
      "colonia": "Los Guerra",
      "postal_code": [
        "88310"
      ]
    },
    {
      "city": "Miguel Aleman",
      "colonia": "Los Lopez",
      "postal_code": [
        "88338"
      ]
    },
    {
      "city": "Miguel Aleman",
      "colonia": "Los Presidentes",
      "postal_code": [
        "88304"
      ]
    },
    {
      "city": "Miguel Aleman",
      "colonia": "Los Trevino",
      "postal_code": [
        "88335"
      ]
    },
    {
      "city": "Miguel Aleman",
      "colonia": "Lucha Social",
      "postal_code": [
        "88307"
      ]
    },
    {
      "city": "Miguel Aleman",
      "colonia": "Mezquital del Norte",
      "postal_code": [
        "88302"
      ]
    },
    {
      "city": "Miguel Aleman",
      "colonia": "Mezquital del Rio",
      "postal_code": [
        "88306"
      ]
    },
    {
      "city": "Miguel Aleman",
      "colonia": "Montebello",
      "postal_code": [
        "88304"
      ]
    },
    {
      "city": "Miguel Aleman",
      "colonia": "Ninos Heroes",
      "postal_code": [
        "88302"
      ]
    },
    {
      "city": "Miguel Aleman",
      "colonia": "Nuevo Amanecer",
      "postal_code": [
        "88303"
      ]
    },
    {
      "city": "Miguel Aleman",
      "colonia": "Nuevo Santander",
      "postal_code": [
        "88302"
      ]
    },
    {
      "city": "Miguel Aleman",
      "colonia": "Plan de Guadalupe",
      "postal_code": [
        "88302"
      ]
    },
    {
      "city": "Miguel Aleman",
      "colonia": "Rio Bravo",
      "postal_code": [
        "88303"
      ]
    },
    {
      "city": "Miguel Aleman",
      "colonia": "Rodriguez",
      "postal_code": [
        "88307"
      ]
    },
    {
      "city": "Miguel Aleman",
      "colonia": "Sabinitos",
      "postal_code": [
        "88307"
      ]
    },
    {
      "city": "Miguel Aleman",
      "colonia": "San Antonio Reyna",
      "postal_code": [
        "88346"
      ]
    },
    {
      "city": "Miguel Aleman",
      "colonia": "Solidaridad",
      "postal_code": [
        "88302"
      ]
    },
    {
      "city": "Miguel Aleman",
      "colonia": "Tamaulipas",
      "postal_code": [
        "88305"
      ]
    },
    {
      "city": "Miguel Aleman",
      "colonia": "Unidad Revolucionaria",
      "postal_code": [
        "88303"
      ]
    },
    {
      "city": "Miguel Aleman",
      "colonia": "Unidos Avanzamos",
      "postal_code": [
        "88310"
      ]
    },
    {
      "city": "Miguel Aleman",
      "colonia": "Villa del Mar",
      "postal_code": [
        "88307"
      ]
    }
  ]
}