{
  "data": [
    {
      "city": "Mineral del Chico",
      "colonia": "Bandola",
      "postal_code": [
        "42124"
      ]
    },
    {
      "city": "Mineral del Chico",
      "colonia": "Benito Juarez",
      "postal_code": [
        "42127"
      ]
    },
    {
      "city": "Mineral del Chico",
      "colonia": "Capula",
      "postal_code": [
        "42125"
      ]
    },
    {
      "city": "Mineral del Chico",
      "colonia": "Carboneras",
      "postal_code": [
        "42124"
      ]
    },
    {
      "city": "Mineral del Chico",
      "colonia": "Carboneras Cueva Blanca",
      "postal_code": [
        "42124"
      ]
    },
    {
      "city": "Mineral del Chico",
      "colonia": "Carboneras la Palma",
      "postal_code": [
        "42124"
      ]
    },
    {
      "city": "Mineral del Chico",
      "colonia": "Carboneras los Lirios",
      "postal_code": [
        "42124"
      ]
    },
    {
      "city": "Mineral del Chico",
      "colonia": "Cebadas",
      "postal_code": [
        "42124"
      ]
    },
    {
      "city": "Mineral del Chico",
      "colonia": "Cerro Alto",
      "postal_code": [
        "42125"
      ]
    },
    {
      "city": "Mineral del Chico",
      "colonia": "Cimbrones",
      "postal_code": [
        "42125"
      ]
    },
    {
      "city": "Mineral del Chico",
      "colonia": "El Calvario",
      "postal_code": [
        "42120"
      ]
    },
    {
      "city": "Mineral del Chico",
      "colonia": "El Jaspe",
      "postal_code": [
        "42125"
      ]
    },
    {
      "city": "Mineral del Chico",
      "colonia": "El Puente",
      "postal_code": [
        "42122"
      ]
    },
    {
      "city": "Mineral del Chico",
      "colonia": "La Estanzuela",
      "postal_code": [
        "42127"
      ]
    },
    {
      "city": "Mineral del Chico",
      "colonia": "La Gran Campana",
      "postal_code": [
        "42122"
      ]
    },
    {
      "city": "Mineral del Chico",
      "colonia": "La Laguna (Carboneras)",
      "postal_code": [
        "42124"
      ]
    },
    {
      "city": "Mineral del Chico",
      "colonia": "La Laguna (La Estanzuela)",
      "postal_code": [
        "42127"
      ]
    },
    {
      "city": "Mineral del Chico",
      "colonia": "La Presa",
      "postal_code": [
        "42122"
      ]
    },
    {
      "city": "Mineral del Chico",
      "colonia": "La Sierra",
      "postal_code": [
        "42120"
      ]
    },
    {
      "city": "Mineral del Chico",
      "colonia": "Las Piletas",
      "postal_code": [
        "42124"
      ]
    },
    {
      "city": "Mineral del Chico",
      "colonia": "Llano de los Ajos",
      "postal_code": [
        "42123"
      ]
    },
    {
      "city": "Mineral del Chico",
      "colonia": "Lo de Sanchez",
      "postal_code": [
        "42120"
      ]
    },
    {
      "city": "Mineral del Chico",
      "colonia": "Loma del Maguey",
      "postal_code": [
        "42123"
      ]
    },
    {
      "city": "Mineral del Chico",
      "colonia": "Longinos",
      "postal_code": [
        "42120"
      ]
    },
    {
      "city": "Mineral del Chico",
      "colonia": "Los Naranjos",
      "postal_code": [
        "42124"
      ]
    },
    {
      "city": "Mineral del Chico",
      "colonia": "Los Ocotes",
      "postal_code": [
        "42122"
      ]
    },
    {
      "city": "Mineral del Chico",
      "colonia": "Manzanas (Barrio de Manzanas)",
      "postal_code": [
        "42125"
      ]
    },
    {
      "city": "Mineral del Chico",
      "colonia": "Mineral del Chico Centro",
      "postal_code": [
        "42120"
      ]
    },
    {
      "city": "Mineral del Chico",
      "colonia": "Pie de la Viga",
      "postal_code": [
        "42123"
      ]
    },
    {
      "city": "Mineral del Chico",
      "colonia": "Plan Grande",
      "postal_code": [
        "42122"
      ]
    },
    {
      "city": "Mineral del Chico",
      "colonia": "San Antonio el Llano",
      "postal_code": [
        "42125"
      ]
    },
    {
      "city": "Mineral del Chico",
      "colonia": "San Francisco",
      "postal_code": [
        "42125"
      ]
    },
    {
      "city": "Mineral del Chico",
      "colonia": "San Jose Capulines",
      "postal_code": [
        "42127"
      ]
    },
    {
      "city": "Mineral del Chico",
      "colonia": "San Sebastian Capulines",
      "postal_code": [
        "42123"
      ]
    },
    {
      "city": "Mineral del Chico",
      "colonia": "San Simon lo de Rojas",
      "postal_code": [
        "42125"
      ]
    },
    {
      "city": "Mineral del Chico",
      "colonia": "Santa Ines",
      "postal_code": [
        "42125"
      ]
    },
    {
      "city": "Mineral del Chico",
      "colonia": "Tierras Coloradas",
      "postal_code": [
        "42123"
      ]
    }
  ]
}