{
  "data": [
    {
      "city": "Navojoa",
      "colonia": "16 de Junio",
      "postal_code": [
        "85893"
      ]
    },
    {
      "city": "Navojoa",
      "colonia": "16 de Septiembre",
      "postal_code": [
        "85895"
      ]
    },
    {
      "city": "Navojoa",
      "colonia": "5 de Junio",
      "postal_code": [
        "85226"
      ]
    },
    {
      "city": "Navojoa",
      "colonia": "Abraham Mendivil Portillo",
      "postal_code": [
        "85226"
      ]
    },
    {
      "city": "Navojoa",
      "colonia": "Ada [Planta Procesadora de Granos]",
      "postal_code": [
        "85226"
      ]
    },
    {
      "city": "Navojoa",
      "colonia": "Adolfo de la Huerta",
      "postal_code": [
        "85222"
      ]
    },
    {
      "city": "Navojoa",
      "colonia": "Aeropuerto",
      "postal_code": [
        "85880"
      ]
    },
    {
      "city": "Navojoa",
      "colonia": "Agiabampo",
      "postal_code": [
        "85233",
        "85239"
      ]
    },
    {
      "city": "Navojoa",
      "colonia": "Agropecuaria Tecorahui",
      "postal_code": [
        "85232"
      ]
    },
    {
      "city": "Navojoa",
      "colonia": "Agua Nueva",
      "postal_code": [
        "85222"
      ]
    },
    {
      "city": "Navojoa",
      "colonia": "Aldegundo",
      "postal_code": [
        "85226"
      ]
    },
    {
      "city": "Navojoa",
      "colonia": "Alfredo Karam",
      "postal_code": [
        "85223"
      ]
    },
    {
      "city": "Navojoa",
      "colonia": "Algodonera",
      "postal_code": [
        "85228"
      ]
    },
    {
      "city": "Navojoa",
      "colonia": "Alinsumos",
      "postal_code": [
        "85232"
      ]
    },
    {
      "city": "Navojoa",
      "colonia": "Allende",
      "postal_code": [
        "85850"
      ]
    },
    {
      "city": "Navojoa",
      "colonia": "Almacenadora de Navojoa",
      "postal_code": [
        "85239"
      ]
    },
    {
      "city": "Navojoa",
      "colonia": "Altamira",
      "postal_code": [
        "85235"
      ]
    },
    {
      "city": "Navojoa",
      "colonia": "alvarez Hermanos",
      "postal_code": [
        "85223",
        "85223",
        "85223"
      ]
    },
    {
      "city": "Navojoa",
      "colonia": "Amador Almada",
      "postal_code": [
        "85223"
      ]
    },
    {
      "city": "Navojoa",
      "colonia": "Ampliacion Beltrones",
      "postal_code": [
        "85860"
      ]
    },
    {
      "city": "Navojoa",
      "colonia": "Antonio Rosales (Las animas)",
      "postal_code": [
        "85224"
      ]
    },
    {
      "city": "Navojoa",
      "colonia": "Aquimulato",
      "postal_code": [
        "85227"
      ]
    },
    {
      "city": "Navojoa",
      "colonia": "Arboledas",
      "postal_code": [
        "85890"
      ]
    },
    {
      "city": "Navojoa",
      "colonia": "Armando Lopez Nogales",
      "postal_code": [
        "85880"
      ]
    },
    {
      "city": "Navojoa",
      "colonia": "Arturo Almada",
      "postal_code": [
        "85224"
      ]
    },
    {
      "city": "Navojoa",
      "colonia": "Aviacion",
      "postal_code": [
        "85840"
      ]
    },
    {
      "city": "Navojoa",
      "colonia": "Avicola Rancho Grande",
      "postal_code": [
        "85236"
      ]
    },
    {
      "city": "Navojoa",
      "colonia": "Avicola Sonqui",
      "postal_code": [
        "85234"
      ]
    },
    {
      "city": "Navojoa",
      "colonia": "Babojori",
      "postal_code": [
        "85232"
      ]
    },
    {
      "city": "Navojoa",
      "colonia": "Bacabachi",
      "postal_code": [
        "85223"
      ]
    },
    {
      "city": "Navojoa",
      "colonia": "Bacabachi (La Granja)",
      "postal_code": [
        "85223"
      ]
    },
    {
      "city": "Navojoa",
      "colonia": "Bacame Nuevo",
      "postal_code": [
        "85236"
      ]
    },
    {
      "city": "Navojoa",
      "colonia": "Baceran",
      "postal_code": [
        "85228"
      ]
    },
    {
      "city": "Navojoa",
      "colonia": "Bachoco",
      "postal_code": [
        "85224"
      ]
    },
    {
      "city": "Navojoa",
      "colonia": "Bachoco Veinticinco Diecisiete",
      "postal_code": [
        "85234"
      ]
    },
    {
      "city": "Navojoa",
      "colonia": "Barebampo",
      "postal_code": [
        "85235"
      ]
    },
    {
      "city": "Navojoa",
      "colonia": "Barrio Cantua",
      "postal_code": [
        "85237"
      ]
    },
    {
      "city": "Navojoa",
      "colonia": "Barrio Corral",
      "postal_code": [
        "85237"
      ]
    },
    {
      "city": "Navojoa",
      "colonia": "Basiabampo",
      "postal_code": [
        "85232"
      ]
    },
    {
      "city": "Navojoa",
      "colonia": "Batayaqui",
      "postal_code": [
        "85227"
      ]
    },
    {
      "city": "Navojoa",
      "colonia": "Beltrones",
      "postal_code": [
        "85860"
      ]
    },
    {
      "city": "Navojoa",
      "colonia": "Bemelabampo",
      "postal_code": [
        "85229"
      ]
    },
    {
      "city": "Navojoa",
      "colonia": "Benito Juarez (La Granja)",
      "postal_code": [
        "85220"
      ]
    },
    {
      "city": "Navojoa",
      "colonia": "Borquez",
      "postal_code": [
        "85224"
      ]
    },
    {
      "city": "Navojoa",
      "colonia": "Boza [Agropecuaria]",
      "postal_code": [
        "85224"
      ]
    },
    {
      "city": "Navojoa",
      "colonia": "Brisas del Valle",
      "postal_code": [
        "85864"
      ]
    },
    {
      "city": "Navojoa",
      "colonia": "Buaraje Viejo",
      "postal_code": [
        "85234"
      ]
    },
    {
      "city": "Navojoa",
      "colonia": "Buenavista",
      "postal_code": [
        "85226",
        "85810"
      ]
    },
    {
      "city": "Navojoa",
      "colonia": "Buenos Aires",
      "postal_code": [
        "85239"
      ]
    },
    {
      "city": "Navojoa",
      "colonia": "Bugambilias",
      "postal_code": [
        "85874"
      ]
    },
    {
      "city": "Navojoa",
      "colonia": "Buiyacusi",
      "postal_code": [
        "85239"
      ]
    },
    {
      "city": "Navojoa",
      "colonia": "Bulabampo",
      "postal_code": [
        "85220"
      ]
    },
    {
      "city": "Navojoa",
      "colonia": "Camino Real",
      "postal_code": [
        "85823"
      ]
    },
    {
      "city": "Navojoa",
      "colonia": "Camoa",
      "postal_code": [
        "85237"
      ]
    },
    {
      "city": "Navojoa",
      "colonia": "Campestre",
      "postal_code": [
        "85823"
      ]
    },
    {
      "city": "Navojoa",
      "colonia": "Campo Aguadulce",
      "postal_code": [
        "85226"
      ]
    },
    {
      "city": "Navojoa",
      "colonia": "Campo Antonio Zazueta (Las Ruinas)",
      "postal_code": [
        "85234"
      ]
    },
    {
      "city": "Navojoa",
      "colonia": "Campo Arvizu",
      "postal_code": [
        "85234"
      ]
    },
    {
      "city": "Navojoa",
      "colonia": "Campo Bojorquez",
      "postal_code": [
        "85224"
      ]
    },
    {
      "city": "Navojoa",
      "colonia": "Campo Chacon",
      "postal_code": [
        "85224"
      ]
    },
    {
      "city": "Navojoa",
      "colonia": "Campo Cuauhtemoc",
      "postal_code": [
        "85234"
      ]
    },
    {
      "city": "Navojoa",
      "colonia": "Campo de Guillermo Giesecke",
      "postal_code": [
        "85226"
      ]
    },
    {
      "city": "Navojoa",
      "colonia": "Campo de Jesus Almada",
      "postal_code": [
        "85224"
      ]
    },
    {
      "city": "Navojoa",
      "colonia": "Campo del Gringo",
      "postal_code": [
        "85234"
      ]
    },
    {
      "city": "Navojoa",
      "colonia": "Campo Girasol",
      "postal_code": [
        "85223"
      ]
    },
    {
      "city": "Navojoa",
      "colonia": "Campo Jose Gastelum",
      "postal_code": [
        "85234"
      ]
    },
    {
      "city": "Navojoa",
      "colonia": "Campo Roberto Rosas",
      "postal_code": [
        "85224"
      ]
    },
    {
      "city": "Navojoa",
      "colonia": "Campo San Francisco",
      "postal_code": [
        "85226"
      ]
    },
    {
      "city": "Navojoa",
      "colonia": "Campo Santa Monica",
      "postal_code": [
        "85224"
      ]
    },
    {
      "city": "Navojoa",
      "colonia": "Campo Valenzuela",
      "postal_code": [
        "85226"
      ]
    },
    {
      "city": "Navojoa",
      "colonia": "Campo Zazueta",
      "postal_code": [
        "85226"
      ]
    },
    {
      "city": "Navojoa",
      "colonia": "Canuto Aguilar (Campo Canuto)",
      "postal_code": [
        "85223"
      ]
    },
    {
      "city": "Navojoa",
      "colonia": "Capetamaya",
      "postal_code": [
        "85224"
      ]
    },
    {
      "city": "Navojoa",
      "colonia": "Capetamaya Granja Rosita (La Rosita)",
      "postal_code": [
        "85224"
      ]
    },
    {
      "city": "Navojoa",
      "colonia": "Capohuiza",
      "postal_code": [
        "85239"
      ]
    },
    {
      "city": "Navojoa",
      "colonia": "Casa Blanca",
      "postal_code": [
        "85224",
        "85227",
        "85235"
      ]
    },
    {
      "city": "Navojoa",
      "colonia": "Caseta de Cobro",
      "postal_code": [
        "85233"
      ]
    },
    {
      "city": "Navojoa",
      "colonia": "Che Guevara",
      "postal_code": [
        "85234"
      ]
    },
    {
      "city": "Navojoa",
      "colonia": "Chibucu",
      "postal_code": [
        "85238"
      ]
    },
    {
      "city": "Navojoa",
      "colonia": "Chihuahuita",
      "postal_code": [
        "85229"
      ]
    },
    {
      "city": "Navojoa",
      "colonia": "Chinobampo",
      "postal_code": [
        "85227"
      ]
    },
    {
      "city": "Navojoa",
      "colonia": "Chinotahueca",
      "postal_code": [
        "85226"
      ]
    },
    {
      "city": "Navojoa",
      "colonia": "Chirajobampo",
      "postal_code": [
        "85224"
      ]
    },
    {
      "city": "Navojoa",
      "colonia": "Choacalle",
      "postal_code": [
        "85220"
      ]
    },
    {
      "city": "Navojoa",
      "colonia": "Cohuirimpo",
      "postal_code": [
        "85228"
      ]
    },
    {
      "city": "Navojoa",
      "colonia": "Colegio del Pacifico",
      "postal_code": [
        "85226"
      ]
    },
    {
      "city": "Navojoa",
      "colonia": "Compuerta Treinta y Ocho",
      "postal_code": [
        "85224"
      ]
    },
    {
      "city": "Navojoa",
      "colonia": "Constitucion",
      "postal_code": [
        "85820"
      ]
    },
    {
      "city": "Navojoa",
      "colonia": "Corrales la Quince",
      "postal_code": [
        "85229"
      ]
    },
    {
      "city": "Navojoa",
      "colonia": "CTM Obrera",
      "postal_code": [
        "85840"
      ]
    },
    {
      "city": "Navojoa",
      "colonia": "Cucajaqui",
      "postal_code": [
        "85220"
      ]
    },
    {
      "city": "Navojoa",
      "colonia": "Cuchilla de Bahuises",
      "postal_code": [
        "85229"
      ]
    },
    {
      "city": "Navojoa",
      "colonia": "Cuchujaqui",
      "postal_code": [
        "85235"
      ]
    },
    {
      "city": "Navojoa",
      "colonia": "Cutataila",
      "postal_code": [
        "85228"
      ]
    },
    {
      "city": "Navojoa",
      "colonia": "Daniel Camacho",
      "postal_code": [
        "85228"
      ]
    },
    {
      "city": "Navojoa",
      "colonia": "Deportiva",
      "postal_code": [
        "85860"
      ]
    },
    {
      "city": "Navojoa",
      "colonia": "DER Agricola",
      "postal_code": [
        "85224"
      ]
    },
    {
      "city": "Navojoa",
      "colonia": "Don Pepe [Hacienda]",
      "postal_code": [
        "85226"
      ]
    },
    {
      "city": "Navojoa",
      "colonia": "Ejido Ignacio Pesqueira",
      "postal_code": [
        "85236"
      ]
    },
    {
      "city": "Navojoa",
      "colonia": "Ejido Revolucion Mexicana",
      "postal_code": [
        "85234"
      ]
    },
    {
      "city": "Navojoa",
      "colonia": "El Abajeno",
      "postal_code": [
        "85224"
      ]
    },
    {
      "city": "Navojoa",
      "colonia": "El Abajeno [Restaurante]",
      "postal_code": [
        "85224"
      ]
    },
    {
      "city": "Navojoa",
      "colonia": "El Alamito",
      "postal_code": [
        "85238"
      ]
    },
    {
      "city": "Navojoa",
      "colonia": "El alamo",
      "postal_code": [
        "85830"
      ]
    },
    {
      "city": "Navojoa",
      "colonia": "El arbol Caido [Restaurante]",
      "postal_code": [
        "85229"
      ]
    },
    {
      "city": "Navojoa",
      "colonia": "El Bachivo",
      "postal_code": [
        "85227"
      ]
    },
    {
      "city": "Navojoa",
      "colonia": "El Barrial",
      "postal_code": [
        "85224",
        "85225",
        "85226"
      ]
    },
    {
      "city": "Navojoa",
      "colonia": "El Barrial Kilometro Doce",
      "postal_code": [
        "85226"
      ]
    },
    {
      "city": "Navojoa",
      "colonia": "El Campito",
      "postal_code": [
        "85229"
      ]
    },
    {
      "city": "Navojoa",
      "colonia": "El Chapote",
      "postal_code": [
        "85238"
      ]
    },
    {
      "city": "Navojoa",
      "colonia": "El Chapulin",
      "postal_code": [
        "85235"
      ]
    },
    {
      "city": "Navojoa",
      "colonia": "El Chilicote",
      "postal_code": [
        "85227"
      ]
    },
    {
      "city": "Navojoa",
      "colonia": "El Ciclon [Avicola]",
      "postal_code": [
        "85224"
      ]
    },
    {
      "city": "Navojoa",
      "colonia": "El Core",
      "postal_code": [
        "85235"
      ]
    },
    {
      "city": "Navojoa",
      "colonia": "El Cuatro",
      "postal_code": [
        "85224"
      ]
    },
    {
      "city": "Navojoa",
      "colonia": "El Cumbro",
      "postal_code": [
        "85228"
      ]
    },
    {
      "city": "Navojoa",
      "colonia": "El Datil",
      "postal_code": [
        "85229"
      ]
    },
    {
      "city": "Navojoa",
      "colonia": "El Dolar",
      "postal_code": [
        "85232"
      ]
    },
    {
      "city": "Navojoa",
      "colonia": "El Gachupin",
      "postal_code": [
        "85234"
      ]
    },
    {
      "city": "Navojoa",
      "colonia": "El Invernadero",
      "postal_code": [
        "85234"
      ]
    },
    {
      "city": "Navojoa",
      "colonia": "El Jijiri",
      "postal_code": [
        "85235"
      ]
    },
    {
      "city": "Navojoa",
      "colonia": "El Jopo",
      "postal_code": [
        "85226"
      ]
    },
    {
      "city": "Navojoa",
      "colonia": "El Limon",
      "postal_code": [
        "85229"
      ]
    },
    {
      "city": "Navojoa",
      "colonia": "El Milagro",
      "postal_code": [
        "85224"
      ]
    },
    {
      "city": "Navojoa",
      "colonia": "El Molino",
      "postal_code": [
        "85229"
      ]
    },
    {
      "city": "Navojoa",
      "colonia": "El Papalote",
      "postal_code": [
        "85224"
      ]
    },
    {
      "city": "Navojoa",
      "colonia": "El Pollin",
      "postal_code": [
        "85232"
      ]
    },
    {
      "city": "Navojoa",
      "colonia": "El Ranchito",
      "postal_code": [
        "85227"
      ]
    },
    {
      "city": "Navojoa",
      "colonia": "El Rancho",
      "postal_code": [
        "85229"
      ]
    },
    {
      "city": "Navojoa",
      "colonia": "El Rancho Sahueso",
      "postal_code": [
        "85238"
      ]
    },
    {
      "city": "Navojoa",
      "colonia": "El Recodo",
      "postal_code": [
        "85228"
      ]
    },
    {
      "city": "Navojoa",
      "colonia": "El Reparo",
      "postal_code": [
        "85223"
      ]
    },
    {
      "city": "Navojoa",
      "colonia": "El Retiro",
      "postal_code": [
        "85233",
        "85233"
      ]
    },
    {
      "city": "Navojoa",
      "colonia": "Elsa",
      "postal_code": [
        "85233"
      ]
    },
    {
      "city": "Navojoa",
      "colonia": "El Sabinito de Tesia (Tesia y Sus Anexos)",
      "postal_code": [
        "85220"
      ]
    },
    {
      "city": "Navojoa",
      "colonia": "El Sabino",
      "postal_code": [
        "85237"
      ]
    },
    {
      "city": "Navojoa",
      "colonia": "El Saneal",
      "postal_code": [
        "85223"
      ]
    },
    {
      "city": "Navojoa",
      "colonia": "El Saneal (La Granja)",
      "postal_code": [
        "85223"
      ]
    },
    {
      "city": "Navojoa",
      "colonia": "El Saucito",
      "postal_code": [
        "85229"
      ]
    },
    {
      "city": "Navojoa",
      "colonia": "El Sauz",
      "postal_code": [
        "85229"
      ]
    },
    {
      "city": "Navojoa",
      "colonia": "El Sifon (Sifon Canal Alto)",
      "postal_code": [
        "85234"
      ]
    },
    {
      "city": "Navojoa",
      "colonia": "El Siviral",
      "postal_code": [
        "85229"
      ]
    },
    {
      "city": "Navojoa",
      "colonia": "El Tablon",
      "postal_code": [
        "85237"
      ]
    },
    {
      "city": "Navojoa",
      "colonia": "El Tecolote",
      "postal_code": [
        "85227",
        "85237"
      ]
    },
    {
      "city": "Navojoa",
      "colonia": "El Tori",
      "postal_code": [
        "85232"
      ]
    },
    {
      "city": "Navojoa",
      "colonia": "El Triunfo",
      "postal_code": [
        "85239"
      ]
    },
    {
      "city": "Navojoa",
      "colonia": "El Viejo Batayaqui",
      "postal_code": [
        "85227"
      ]
    },
    {
      "city": "Navojoa",
      "colonia": "Engorda Campoy",
      "postal_code": [
        "85233"
      ]
    },
    {
      "city": "Navojoa",
      "colonia": "Engorda Yoreme",
      "postal_code": [
        "85233"
      ]
    },
    {
      "city": "Navojoa",
      "colonia": "Epifanio Zazueta",
      "postal_code": [
        "85226"
      ]
    },
    {
      "city": "Navojoa",
      "colonia": "Esperancita",
      "postal_code": [
        "85233"
      ]
    },
    {
      "city": "Navojoa",
      "colonia": "Estacion de FFCC Seccion Dieciocho",
      "postal_code": [
        "85233"
      ]
    },
    {
      "city": "Navojoa",
      "colonia": "Estacion Masiaca",
      "postal_code": [
        "85220"
      ]
    },
    {
      "city": "Navojoa",
      "colonia": "Estacion Velderrain",
      "postal_code": [
        "85233"
      ]
    },
    {
      "city": "Navojoa",
      "colonia": "Estadio Viejo",
      "postal_code": [
        "85800"
      ]
    },
    {
      "city": "Navojoa",
      "colonia": "Etchohuaquila",
      "postal_code": [
        "85233"
      ]
    },
    {
      "city": "Navojoa",
      "colonia": "Etchomocha",
      "postal_code": [
        "85227"
      ]
    },
    {
      "city": "Navojoa",
      "colonia": "Eugenia",
      "postal_code": [
        "85233"
      ]
    },
    {
      "city": "Navojoa",
      "colonia": "Familia Felix Cervantes",
      "postal_code": [
        "85234"
      ]
    },
    {
      "city": "Navojoa",
      "colonia": "Familia Ozuna Ayala",
      "postal_code": [
        "85228"
      ]
    },
    {
      "city": "Navojoa",
      "colonia": "Felipe angeles",
      "postal_code": [
        "85220"
      ]
    },
    {
      "city": "Navojoa",
      "colonia": "Feriva",
      "postal_code": [
        "85234"
      ]
    },
    {
      "city": "Navojoa",
      "colonia": "Fernando Yepiz Rosas",
      "postal_code": [
        "85224"
      ]
    },
    {
      "city": "Navojoa",
      "colonia": "Finca Real",
      "postal_code": [
        "85843"
      ]
    },
    {
      "city": "Navojoa",
      "colonia": "Fitosanitaria (Estacion Cuarentenaria)",
      "postal_code": [
        "85239"
      ]
    },
    {
      "city": "Navojoa",
      "colonia": "FOVISSSTE",
      "postal_code": [
        "85864"
      ]
    },
    {
      "city": "Navojoa",
      "colonia": "Francisco Clemen Bretano",
      "postal_code": [
        "85228"
      ]
    },
    {
      "city": "Navojoa",
      "colonia": "Francisco I. Madero Dos",
      "postal_code": [
        "85223"
      ]
    },
    {
      "city": "Navojoa",
      "colonia": "Francisco Villa",
      "postal_code": [
        "85880"
      ]
    },
    {
      "city": "Navojoa",
      "colonia": "Fundicion",
      "postal_code": [
        "85233"
      ]
    },
    {
      "city": "Navojoa",
      "colonia": "Gabriela",
      "postal_code": [
        "85233"
      ]
    },
    {
      "city": "Navojoa",
      "colonia": "General Gabriel Leyva Solano (Gabriel Leyva)",
      "postal_code": [
        "85232"
      ]
    },
    {
      "city": "Navojoa",
      "colonia": "Genes",
      "postal_code": [
        "85233"
      ]
    },
    {
      "city": "Navojoa",
      "colonia": "Geni-Kowi",
      "postal_code": [
        "85234"
      ]
    },
    {
      "city": "Navojoa",
      "colonia": "German Corral",
      "postal_code": [
        "85224"
      ]
    },
    {
      "city": "Navojoa",
      "colonia": "Gilberto Barcelo",
      "postal_code": [
        "85236"
      ]
    },
    {
      "city": "Navojoa",
      "colonia": "Graciano Sanchez (Yorigibe)",
      "postal_code": [
        "85235"
      ]
    },
    {
      "city": "Navojoa",
      "colonia": "Granja Sonqui (La Tuna)",
      "postal_code": [
        "85233"
      ]
    },
    {
      "city": "Navojoa",
      "colonia": "Guacaporo (Bacaporo)",
      "postal_code": [
        "85220"
      ]
    },
    {
      "city": "Navojoa",
      "colonia": "Guadalupe",
      "postal_code": [
        "85226"
      ]
    },
    {
      "city": "Navojoa",
      "colonia": "Guadalupe de Juarez",
      "postal_code": [
        "85233"
      ]
    },
    {
      "city": "Navojoa",
      "colonia": "Guadalupe Sonqui",
      "postal_code": [
        "85233"
      ]
    },
    {
      "city": "Navojoa",
      "colonia": "Guaymitas",
      "postal_code": [
        "85230"
      ]
    },
    {
      "city": "Navojoa",
      "colonia": "Hacienda San Antonio",
      "postal_code": [
        "85222"
      ]
    },
    {
      "city": "Navojoa",
      "colonia": "Hacienda Vieja",
      "postal_code": [
        "85826"
      ]
    },
    {
      "city": "Navojoa",
      "colonia": "Hector Arreola",
      "postal_code": [
        "85226"
      ]
    },
    {
      "city": "Navojoa",
      "colonia": "Hidalgo",
      "postal_code": [
        "85840"
      ]
    },
    {
      "city": "Navojoa",
      "colonia": "Huasaguari",
      "postal_code": [
        "85222"
      ]
    },
    {
      "city": "Navojoa",
      "colonia": "Huebampo",
      "postal_code": [
        "85220"
      ]
    },
    {
      "city": "Navojoa",
      "colonia": "Huerta",
      "postal_code": [
        "85228"
      ]
    },
    {
      "city": "Navojoa",
      "colonia": "Huerta Aguilera",
      "postal_code": [
        "85229"
      ]
    },
    {
      "city": "Navojoa",
      "colonia": "Huiribis",
      "postal_code": [
        "85220"
      ]
    },
    {
      "city": "Navojoa",
      "colonia": "Ignacio Pablos",
      "postal_code": [
        "85234"
      ]
    },
    {
      "city": "Navojoa",
      "colonia": "Indeur",
      "postal_code": [
        "85890"
      ]
    },
    {
      "city": "Navojoa",
      "colonia": "INFONAVIT",
      "postal_code": [
        "85890"
      ]
    },
    {
      "city": "Navojoa",
      "colonia": "Itson",
      "postal_code": [
        "85860"
      ]
    },
    {
      "city": "Navojoa",
      "colonia": "Jacarandas",
      "postal_code": [
        "85880"
      ]
    },
    {
      "city": "Navojoa",
      "colonia": "Jacarandas II",
      "postal_code": [
        "85880"
      ]
    },
    {
      "city": "Navojoa",
      "colonia": "Jaitaca",
      "postal_code": [
        "85235"
      ]
    },
    {
      "city": "Navojoa",
      "colonia": "Joaquin Amaro",
      "postal_code": [
        "85234"
      ]
    },
    {
      "city": "Navojoa",
      "colonia": "Jopopaco",
      "postal_code": [
        "85220"
      ]
    },
    {
      "city": "Navojoa",
      "colonia": "Josonteco",
      "postal_code": [
        "85229"
      ]
    },
    {
      "city": "Navojoa",
      "colonia": "Jostahueca",
      "postal_code": [
        "85233"
      ]
    },
    {
      "city": "Navojoa",
      "colonia": "Juan Carlos Cuevas [Empacadora]",
      "postal_code": [
        "85239"
      ]
    },
    {
      "city": "Navojoa",
      "colonia": "Juan Diego",
      "postal_code": [
        "85235"
      ]
    },
    {
      "city": "Navojoa",
      "colonia": "Juarez",
      "postal_code": [
        "85870"
      ]
    },
    {
      "city": "Navojoa",
      "colonia": "Junelancahui (Joconas)",
      "postal_code": [
        "85227"
      ]
    },
    {
      "city": "Navojoa",
      "colonia": "Jupacobe",
      "postal_code": [
        "85226"
      ]
    },
    {
      "city": "Navojoa",
      "colonia": "Jusibampito",
      "postal_code": [
        "85222"
      ]
    },
    {
      "city": "Navojoa",
      "colonia": "Jusibampo",
      "postal_code": [
        "85227",
        "85235"
      ]
    },
    {
      "city": "Navojoa",
      "colonia": "J y J Machinery",
      "postal_code": [
        "85229"
      ]
    },
    {
      "city": "Navojoa",
      "colonia": "Kilometro Catorce",
      "postal_code": [
        "85226"
      ]
    },
    {
      "city": "Navojoa",
      "colonia": "Kutantaka",
      "postal_code": [
        "85228"
      ]
    },
    {
      "city": "Navojoa",
      "colonia": "La Aguja",
      "postal_code": [
        "85222"
      ]
    },
    {
      "city": "Navojoa",
      "colonia": "La Batalla",
      "postal_code": [
        "85236"
      ]
    },
    {
      "city": "Navojoa",
      "colonia": "La Bomba",
      "postal_code": [
        "85226"
      ]
    },
    {
      "city": "Navojoa",
      "colonia": "La Bombita",
      "postal_code": [
        "85233"
      ]
    },
    {
      "city": "Navojoa",
      "colonia": "La Choya 4",
      "postal_code": [
        "85233"
      ]
    },
    {
      "city": "Navojoa",
      "colonia": "La Cruz de Rosales",
      "postal_code": [
        "85230"
      ]
    },
    {
      "city": "Navojoa",
      "colonia": "La Encantada",
      "postal_code": [
        "85830"
      ]
    },
    {
      "city": "Navojoa",
      "colonia": "La Ensenada",
      "postal_code": [
        "85235"
      ]
    },
    {
      "city": "Navojoa",
      "colonia": "La Esmeralda",
      "postal_code": [
        "85222"
      ]
    },
    {
      "city": "Navojoa",
      "colonia": "La Esperanza",
      "postal_code": [
        "85223"
      ]
    },
    {
      "city": "Navojoa",
      "colonia": "La Esquina Valdez (Puente Valdez)",
      "postal_code": [
        "85223"
      ]
    },
    {
      "city": "Navojoa",
      "colonia": "La Finca",
      "postal_code": [
        "85220"
      ]
    },
    {
      "city": "Navojoa",
      "colonia": "La Fortuna",
      "postal_code": [
        "85227"
      ]
    },
    {
      "city": "Navojoa",
      "colonia": "La Guadalupana",
      "postal_code": [
        "85880"
      ]
    },
    {
      "city": "Navojoa",
      "colonia": "La Herradura",
      "postal_code": [
        "85843"
      ]
    },
    {
      "city": "Navojoa",
      "colonia": "La Huerta",
      "postal_code": [
        "85224"
      ]
    },
    {
      "city": "Navojoa",
      "colonia": "La Joya",
      "postal_code": [
        "85874"
      ]
    },
    {
      "city": "Navojoa",
      "colonia": "La Labor de Santa Rosa",
      "postal_code": [
        "85235"
      ]
    },
    {
      "city": "Navojoa",
      "colonia": "La Laguna de Tesia",
      "postal_code": [
        "85238"
      ]
    },
    {
      "city": "Navojoa",
      "colonia": "La Laguna Mondaca",
      "postal_code": [
        "85234"
      ]
    },
    {
      "city": "Navojoa",
      "colonia": "Lamberto Arvizu",
      "postal_code": [
        "85234"
      ]
    },
    {
      "city": "Navojoa",
      "colonia": "La Pastera",
      "postal_code": [
        "85234"
      ]
    },
    {
      "city": "Navojoa",
      "colonia": "La Pera",
      "postal_code": [
        "85235"
      ]
    },
    {
      "city": "Navojoa",
      "colonia": "La Perita",
      "postal_code": [
        "85235"
      ]
    },
    {
      "city": "Navojoa",
      "colonia": "La Potable",
      "postal_code": [
        "85223",
        "85223"
      ]
    },
    {
      "city": "Navojoa",
      "colonia": "La Quince",
      "postal_code": [
        "85229"
      ]
    },
    {
      "city": "Navojoa",
      "colonia": "Las Amapas (Rancho el Jito)",
      "postal_code": [
        "85220"
      ]
    },
    {
      "city": "Navojoa",
      "colonia": "La Sandia",
      "postal_code": [
        "85233"
      ]
    },
    {
      "city": "Navojoa",
      "colonia": "Las Bombas",
      "postal_code": [
        "85223",
        "85237"
      ]
    },
    {
      "city": "Navojoa",
      "colonia": "Las Caballerizas (Campo Ruiz)",
      "postal_code": [
        "85223"
      ]
    },
    {
      "city": "Navojoa",
      "colonia": "Las Carolinas (Cahurara) [Huerta]",
      "postal_code": [
        "85226"
      ]
    },
    {
      "city": "Navojoa",
      "colonia": "Las Chivas",
      "postal_code": [
        "85227"
      ]
    },
    {
      "city": "Navojoa",
      "colonia": "Las Dos Palmas",
      "postal_code": [
        "85226"
      ]
    },
    {
      "city": "Navojoa",
      "colonia": "Las Flores",
      "postal_code": [
        "85220"
      ]
    },
    {
      "city": "Navojoa",
      "colonia": "Las Guasimas (El Japones)",
      "postal_code": [
        "85238"
      ]
    },
    {
      "city": "Navojoa",
      "colonia": "Las Guasimas [Rancho]",
      "postal_code": [
        "85238"
      ]
    },
    {
      "city": "Navojoa",
      "colonia": "Las Hurracas",
      "postal_code": [
        "85238"
      ]
    },
    {
      "city": "Navojoa",
      "colonia": "Las Iguanas",
      "postal_code": [
        "85232"
      ]
    },
    {
      "city": "Navojoa",
      "colonia": "Las Lajas",
      "postal_code": [
        "85235"
      ]
    },
    {
      "city": "Navojoa",
      "colonia": "Las Milpas",
      "postal_code": [
        "85222"
      ]
    },
    {
      "city": "Navojoa",
      "colonia": "La Soledad",
      "postal_code": [
        "85227"
      ]
    },
    {
      "city": "Navojoa",
      "colonia": "Las Pilas",
      "postal_code": [
        "85235",
        "85237"
      ]
    },
    {
      "city": "Navojoa",
      "colonia": "Las Pilitas",
      "postal_code": [
        "85239"
      ]
    },
    {
      "city": "Navojoa",
      "colonia": "Las Tierritas",
      "postal_code": [
        "85228"
      ]
    },
    {
      "city": "Navojoa",
      "colonia": "Las Viboras",
      "postal_code": [
        "85222"
      ]
    },
    {
      "city": "Navojoa",
      "colonia": "Licenciado Luis Echeverria alvarez",
      "postal_code": [
        "85223"
      ]
    },
    {
      "city": "Navojoa",
      "colonia": "Licenciado Miguel de la Madrid Hurtado",
      "postal_code": [
        "85234"
      ]
    },
    {
      "city": "Navojoa",
      "colonia": "Linda Vista",
      "postal_code": [
        "85236"
      ]
    },
    {
      "city": "Navojoa",
      "colonia": "Lolita",
      "postal_code": [
        "85224"
      ]
    },
    {
      "city": "Navojoa",
      "colonia": "Loma del Refugio",
      "postal_code": [
        "85239"
      ]
    },
    {
      "city": "Navojoa",
      "colonia": "Loma Linda",
      "postal_code": [
        "85233"
      ]
    },
    {
      "city": "Navojoa",
      "colonia": "Los Aguacates [Huerta]",
      "postal_code": [
        "85229"
      ]
    },
    {
      "city": "Navojoa",
      "colonia": "Los Arcos",
      "postal_code": [
        "85825"
      ]
    },
    {
      "city": "Navojoa",
      "colonia": "Los Arvizu",
      "postal_code": [
        "85226"
      ]
    },
    {
      "city": "Navojoa",
      "colonia": "Los Bahuises",
      "postal_code": [
        "85230"
      ]
    },
    {
      "city": "Navojoa",
      "colonia": "Los Batequis",
      "postal_code": [
        "85233"
      ]
    },
    {
      "city": "Navojoa",
      "colonia": "Los Borquez",
      "postal_code": [
        "85224"
      ]
    },
    {
      "city": "Navojoa",
      "colonia": "Los Briseno",
      "postal_code": [
        "85229"
      ]
    },
    {
      "city": "Navojoa",
      "colonia": "Los Buayums",
      "postal_code": [
        "85223"
      ]
    },
    {
      "city": "Navojoa",
      "colonia": "Los Buhitos",
      "postal_code": [
        "85233"
      ]
    },
    {
      "city": "Navojoa",
      "colonia": "Los Cuates",
      "postal_code": [
        "85232"
      ]
    },
    {
      "city": "Navojoa",
      "colonia": "Los Cuatro",
      "postal_code": [
        "85227"
      ]
    },
    {
      "city": "Navojoa",
      "colonia": "Los Girasoles",
      "postal_code": [
        "85874"
      ]
    },
    {
      "city": "Navojoa",
      "colonia": "Los Gonzalez",
      "postal_code": [
        "85220"
      ]
    },
    {
      "city": "Navojoa",
      "colonia": "Los Jitos [Granja]",
      "postal_code": [
        "85224"
      ]
    },
    {
      "city": "Navojoa",
      "colonia": "Los Laureles",
      "postal_code": [
        "85874"
      ]
    },
    {
      "city": "Navojoa",
      "colonia": "Los Limones",
      "postal_code": [
        "85229",
        "85238"
      ]
    },
    {
      "city": "Navojoa",
      "colonia": "Los Magueyes",
      "postal_code": [
        "85233"
      ]
    },
    {
      "city": "Navojoa",
      "colonia": "Los Mochocolis",
      "postal_code": [
        "85220"
      ]
    },
    {
      "city": "Navojoa",
      "colonia": "Los Naranjos",
      "postal_code": [
        "85835"
      ]
    },
    {
      "city": "Navojoa",
      "colonia": "Los Parosis",
      "postal_code": [
        "85226"
      ]
    },
    {
      "city": "Navojoa",
      "colonia": "Los Pinos",
      "postal_code": [
        "85224",
        "85226"
      ]
    },
    {
      "city": "Navojoa",
      "colonia": "Macias",
      "postal_code": [
        "85223",
        "85223"
      ]
    },
    {
      "city": "Navojoa",
      "colonia": "Manuel Godinez",
      "postal_code": [
        "85226"
      ]
    },
    {
      "city": "Navojoa",
      "colonia": "Margarita",
      "postal_code": [
        "85229",
        "85229",
        "85232"
      ]
    },
    {
      "city": "Navojoa",
      "colonia": "Mario Ramirez Rincon",
      "postal_code": [
        "85228"
      ]
    },
    {
      "city": "Navojoa",
      "colonia": "Martinez",
      "postal_code": [
        "85224"
      ]
    },
    {
      "city": "Navojoa",
      "colonia": "Masiaca",
      "postal_code": [
        "85220"
      ]
    },
    {
      "city": "Navojoa",
      "colonia": "Masubampo (Nasubampo)",
      "postal_code": [
        "85227"
      ]
    },
    {
      "city": "Navojoa",
      "colonia": "Mazolay",
      "postal_code": [
        "85224"
      ]
    },
    {
      "city": "Navojoa",
      "colonia": "Mezquital de Abajo",
      "postal_code": [
        "85229"
      ]
    },
    {
      "city": "Navojoa",
      "colonia": "Mezquital de Buiyacusi",
      "postal_code": [
        "85239"
      ]
    },
    {
      "city": "Navojoa",
      "colonia": "Mezquital de Pueblo Viejo",
      "postal_code": [
        "85835"
      ]
    },
    {
      "city": "Navojoa",
      "colonia": "Mezquital de Tesia",
      "postal_code": [
        "85238"
      ]
    },
    {
      "city": "Navojoa",
      "colonia": "Miguel de la Madrid Dos",
      "postal_code": [
        "85234",
        "85234"
      ]
    },
    {
      "city": "Navojoa",
      "colonia": "Miguel de la Madrid Uno",
      "postal_code": [
        "85234"
      ]
    },
    {
      "city": "Navojoa",
      "colonia": "Miguel Hidalgo",
      "postal_code": [
        "85227"
      ]
    },
    {
      "city": "Navojoa",
      "colonia": "Minas de Arena",
      "postal_code": [
        "85890"
      ]
    },
    {
      "city": "Navojoa",
      "colonia": "Miravalle",
      "postal_code": [
        "85850"
      ]
    },
    {
      "city": "Navojoa",
      "colonia": "Misioneros",
      "postal_code": [
        "85894"
      ]
    },
    {
      "city": "Navojoa",
      "colonia": "Misioneros Del Sur",
      "postal_code": [
        "85894"
      ]
    },
    {
      "city": "Navojoa",
      "colonia": "Mision Salvatierra",
      "postal_code": [
        "85843"
      ]
    },
    {
      "city": "Navojoa",
      "colonia": "Mocuzarit",
      "postal_code": [
        "85850"
      ]
    },
    {
      "city": "Navojoa",
      "colonia": "Moderna",
      "postal_code": [
        "85840"
      ]
    },
    {
      "city": "Navojoa",
      "colonia": "Molino de Almada",
      "postal_code": [
        "85224"
      ]
    },
    {
      "city": "Navojoa",
      "colonia": "Musuabampo",
      "postal_code": [
        "85233"
      ]
    },
    {
      "city": "Navojoa",
      "colonia": "Nacapul",
      "postal_code": [
        "85224"
      ]
    },
    {
      "city": "Navojoa",
      "colonia": "Nachuquis (San Antonio Nachuquis)",
      "postal_code": [
        "85228"
      ]
    },
    {
      "city": "Navojoa",
      "colonia": "Navarro",
      "postal_code": [
        "85226"
      ]
    },
    {
      "city": "Navojoa",
      "colonia": "Navojoa",
      "postal_code": [
        "85226"
      ]
    },
    {
      "city": "Navojoa",
      "colonia": "Navojoa Centro",
      "postal_code": [
        "85800"
      ]
    },
    {
      "city": "Navojoa",
      "colonia": "Navomora",
      "postal_code": [
        "85236"
      ]
    },
    {
      "city": "Navojoa",
      "colonia": "Nogalitos",
      "postal_code": [
        "85840"
      ]
    },
    {
      "city": "Navojoa",
      "colonia": "Norisina",
      "postal_code": [
        "85224"
      ]
    },
    {
      "city": "Navojoa",
      "colonia": "Nueva Generacion",
      "postal_code": [
        "85895"
      ]
    },
    {
      "city": "Navojoa",
      "colonia": "Oviachic",
      "postal_code": [
        "85234"
      ]
    },
    {
      "city": "Navojoa",
      "colonia": "Oviachic 2",
      "postal_code": [
        "85234"
      ]
    },
    {
      "city": "Navojoa",
      "colonia": "Palo Blanco",
      "postal_code": [
        "85235"
      ]
    },
    {
      "city": "Navojoa",
      "colonia": "Parque Industrial",
      "postal_code": [
        "85895"
      ]
    },
    {
      "city": "Navojoa",
      "colonia": "Pedro Almada",
      "postal_code": [
        "85224"
      ]
    },
    {
      "city": "Navojoa",
      "colonia": "Pedro [Porcina]",
      "postal_code": [
        "85229"
      ]
    },
    {
      "city": "Navojoa",
      "colonia": "Piedra Baya",
      "postal_code": [
        "85220"
      ]
    },
    {
      "city": "Navojoa",
      "colonia": "Plano Oriente",
      "postal_code": [
        "85223"
      ]
    },
    {
      "city": "Navojoa",
      "colonia": "Planta de Aguamonia",
      "postal_code": [
        "85234"
      ]
    },
    {
      "city": "Navojoa",
      "colonia": "Planta NOROTOSA",
      "postal_code": [
        "85222"
      ]
    },
    {
      "city": "Navojoa",
      "colonia": "Porcina Cocutec",
      "postal_code": [
        "85227"
      ]
    },
    {
      "city": "Navojoa",
      "colonia": "Pozo Dulce",
      "postal_code": [
        "85236"
      ]
    },
    {
      "city": "Navojoa",
      "colonia": "Presa Nueva",
      "postal_code": [
        "85220"
      ]
    },
    {
      "city": "Navojoa",
      "colonia": "Primero de Abril",
      "postal_code": [
        "85224"
      ]
    },
    {
      "city": "Navojoa",
      "colonia": "Privada del Pedregal",
      "postal_code": [
        "85894"
      ]
    },
    {
      "city": "Navojoa",
      "colonia": "Pueblo Mayo",
      "postal_code": [
        "85236"
      ]
    },
    {
      "city": "Navojoa",
      "colonia": "Pueblo Nuevo",
      "postal_code": [
        "85810"
      ]
    },
    {
      "city": "Navojoa",
      "colonia": "Pueblo Viejo",
      "postal_code": [
        "85845"
      ]
    },
    {
      "city": "Navojoa",
      "colonia": "Puente San Ignacio",
      "postal_code": [
        "85223"
      ]
    },
    {
      "city": "Navojoa",
      "colonia": "Punta de la Laguna",
      "postal_code": [
        "85228"
      ]
    },
    {
      "city": "Navojoa",
      "colonia": "Querobabi [Campo Agricola]",
      "postal_code": [
        "85228"
      ]
    },
    {
      "city": "Navojoa",
      "colonia": "Quinta Angelina",
      "postal_code": [
        "85229"
      ]
    },
    {
      "city": "Navojoa",
      "colonia": "Rabago [Campo Agricola]",
      "postal_code": [
        "85224"
      ]
    },
    {
      "city": "Navojoa",
      "colonia": "Ramon Zazueta",
      "postal_code": [
        "85224"
      ]
    },
    {
      "city": "Navojoa",
      "colonia": "Rancheria",
      "postal_code": [
        "85235"
      ]
    },
    {
      "city": "Navojoa",
      "colonia": "Rancho Atalaya",
      "postal_code": [
        "85222"
      ]
    },
    {
      "city": "Navojoa",
      "colonia": "Rancho Camargo",
      "postal_code": [
        "85228"
      ]
    },
    {
      "city": "Navojoa",
      "colonia": "Rancho de los Gonzalez",
      "postal_code": [
        "85224"
      ]
    },
    {
      "city": "Navojoa",
      "colonia": "Rancho del Padre",
      "postal_code": [
        "85228"
      ]
    },
    {
      "city": "Navojoa",
      "colonia": "Rancho las Granjas",
      "postal_code": [
        "85235"
      ]
    },
    {
      "city": "Navojoa",
      "colonia": "Rancho Nuevo",
      "postal_code": [
        "85222"
      ]
    },
    {
      "city": "Navojoa",
      "colonia": "Rancho Ojeda",
      "postal_code": [
        "85235"
      ]
    },
    {
      "city": "Navojoa",
      "colonia": "Rancho San Jose",
      "postal_code": [
        "85227"
      ]
    },
    {
      "city": "Navojoa",
      "colonia": "Raymundo Lopez",
      "postal_code": [
        "85236"
      ]
    },
    {
      "city": "Navojoa",
      "colonia": "Reforma",
      "postal_code": [
        "85830"
      ]
    },
    {
      "city": "Navojoa",
      "colonia": "Residencial La Huerta",
      "postal_code": [
        "85835"
      ]
    },
    {
      "city": "Navojoa",
      "colonia": "Residencial Santa Maria",
      "postal_code": [
        "85843"
      ]
    },
    {
      "city": "Navojoa",
      "colonia": "Robinson",
      "postal_code": [
        "85226"
      ]
    },
    {
      "city": "Navojoa",
      "colonia": "Rodolfo Rosas",
      "postal_code": [
        "85224"
      ]
    },
    {
      "city": "Navojoa",
      "colonia": "Rosales",
      "postal_code": [
        "85239",
        "85850"
      ]
    },
    {
      "city": "Navojoa",
      "colonia": "Rosario Ruelas",
      "postal_code": [
        "85890"
      ]
    },
    {
      "city": "Navojoa",
      "colonia": "Ruben Valenzuela",
      "postal_code": [
        "85225"
      ]
    },
    {
      "city": "Navojoa",
      "colonia": "Sahuaro",
      "postal_code": [
        "85220"
      ]
    },
    {
      "city": "Navojoa",
      "colonia": "San Alfonso",
      "postal_code": [
        "85225",
        "85227"
      ]
    },
    {
      "city": "Navojoa",
      "colonia": "San Antonio de los Ibarra (San Antonio)",
      "postal_code": [
        "85222"
      ]
    },
    {
      "city": "Navojoa",
      "colonia": "San Carlos Cuatro [Porcina]",
      "postal_code": [
        "85238"
      ]
    },
    {
      "city": "Navojoa",
      "colonia": "San Carlos Tres [Porcina]",
      "postal_code": [
        "85238"
      ]
    },
    {
      "city": "Navojoa",
      "colonia": "San Francisco",
      "postal_code": [
        "85233",
        "85238"
      ]
    },
    {
      "city": "Navojoa",
      "colonia": "San Gerardo",
      "postal_code": [
        "85226"
      ]
    },
    {
      "city": "Navojoa",
      "colonia": "San German",
      "postal_code": [
        "85233"
      ]
    },
    {
      "city": "Navojoa",
      "colonia": "San Ignacio Cohuirimpo",
      "postal_code": [
        "85826"
      ]
    },
    {
      "city": "Navojoa",
      "colonia": "San Jose",
      "postal_code": [
        "85226",
        "85226"
      ]
    },
    {
      "city": "Navojoa",
      "colonia": "San Jose Chinotahueca",
      "postal_code": [
        "85226"
      ]
    },
    {
      "city": "Navojoa",
      "colonia": "San Josecito",
      "postal_code": [
        "85220"
      ]
    },
    {
      "city": "Navojoa",
      "colonia": "San Jose Masiaca",
      "postal_code": [
        "85220"
      ]
    },
    {
      "city": "Navojoa",
      "colonia": "San Juan",
      "postal_code": [
        "85227",
        "85239"
      ]
    },
    {
      "city": "Navojoa",
      "colonia": "San Juan (La Noria)",
      "postal_code": [
        "85223"
      ]
    },
    {
      "city": "Navojoa",
      "colonia": "San Martin",
      "postal_code": [
        "85232"
      ]
    },
    {
      "city": "Navojoa",
      "colonia": "San Martin Chuachora",
      "postal_code": [
        "85223"
      ]
    },
    {
      "city": "Navojoa",
      "colonia": "San Pedrito",
      "postal_code": [
        "85220"
      ]
    },
    {
      "city": "Navojoa",
      "colonia": "San Ricardo",
      "postal_code": [
        "85233"
      ]
    },
    {
      "city": "Navojoa",
      "colonia": "Santa Anita",
      "postal_code": [
        "85226",
        "85229"
      ]
    },
    {
      "city": "Navojoa",
      "colonia": "Santa Barbara",
      "postal_code": [
        "85230",
        "85237",
        "85870"
      ]
    },
    {
      "city": "Navojoa",
      "colonia": "Santa Fe",
      "postal_code": [
        "85826"
      ]
    },
    {
      "city": "Navojoa",
      "colonia": "Santa Isabel",
      "postal_code": [
        "85226",
        "85228",
        "85238"
      ]
    },
    {
      "city": "Navojoa",
      "colonia": "Santa Isabel (Los Cocos)",
      "postal_code": [
        "85224"
      ]
    },
    {
      "city": "Navojoa",
      "colonia": "Santa Maria",
      "postal_code": [
        "85229",
        "85235"
      ]
    },
    {
      "city": "Navojoa",
      "colonia": "Santa Maria del Buaraje",
      "postal_code": [
        "85233"
      ]
    },
    {
      "city": "Navojoa",
      "colonia": "Santa Rosa",
      "postal_code": [
        "85235"
      ]
    },
    {
      "city": "Navojoa",
      "colonia": "Sapochopo",
      "postal_code": [
        "85225"
      ]
    },
    {
      "city": "Navojoa",
      "colonia": "Sapomora",
      "postal_code": [
        "85226"
      ]
    },
    {
      "city": "Navojoa",
      "colonia": "Saucobe",
      "postal_code": [
        "85224"
      ]
    },
    {
      "city": "Navojoa",
      "colonia": "Sibacobe",
      "postal_code": [
        "85238"
      ]
    },
    {
      "city": "Navojoa",
      "colonia": "Sicoma",
      "postal_code": [
        "85226"
      ]
    },
    {
      "city": "Navojoa",
      "colonia": "Sicoma (Bachoco)",
      "postal_code": [
        "85226"
      ]
    },
    {
      "city": "Navojoa",
      "colonia": "Sinahuisa",
      "postal_code": [
        "85224"
      ]
    },
    {
      "city": "Navojoa",
      "colonia": "Singapur",
      "postal_code": [
        "85227"
      ]
    },
    {
      "city": "Navojoa",
      "colonia": "Siquisiva",
      "postal_code": [
        "85237"
      ]
    },
    {
      "city": "Navojoa",
      "colonia": "SONMEX [Industrias]",
      "postal_code": [
        "85227"
      ]
    },
    {
      "city": "Navojoa",
      "colonia": "Sonora",
      "postal_code": [
        "85890"
      ]
    },
    {
      "city": "Navojoa",
      "colonia": "Sonora Progresista",
      "postal_code": [
        "85890"
      ]
    },
    {
      "city": "Navojoa",
      "colonia": "SOP",
      "postal_code": [
        "85890"
      ]
    },
    {
      "city": "Navojoa",
      "colonia": "Susana",
      "postal_code": [
        "85233"
      ]
    },
    {
      "city": "Navojoa",
      "colonia": "Tamazula",
      "postal_code": [
        "85233"
      ]
    },
    {
      "city": "Navojoa",
      "colonia": "Teachive",
      "postal_code": [
        "85222"
      ]
    },
    {
      "city": "Navojoa",
      "colonia": "Tepeyac",
      "postal_code": [
        "85894"
      ]
    },
    {
      "city": "Navojoa",
      "colonia": "Tesia",
      "postal_code": [
        "85238"
      ]
    },
    {
      "city": "Navojoa",
      "colonia": "Tesotahueca",
      "postal_code": [
        "85228"
      ]
    },
    {
      "city": "Navojoa",
      "colonia": "Tessenderlo Kerley",
      "postal_code": [
        "85233"
      ]
    },
    {
      "city": "Navojoa",
      "colonia": "Tetaboca",
      "postal_code": [
        "85894"
      ]
    },
    {
      "city": "Navojoa",
      "colonia": "Tetacruz",
      "postal_code": [
        "85224"
      ]
    },
    {
      "city": "Navojoa",
      "colonia": "Tetanchopo",
      "postal_code": [
        "85827"
      ]
    },
    {
      "city": "Navojoa",
      "colonia": "Tetapeche",
      "postal_code": [
        "85235"
      ]
    },
    {
      "city": "Navojoa",
      "colonia": "Tierra Blanca",
      "postal_code": [
        "85235",
        "85820"
      ]
    },
    {
      "city": "Navojoa",
      "colonia": "Tierra y Libertad",
      "postal_code": [
        "85880"
      ]
    },
    {
      "city": "Navojoa",
      "colonia": "Tiqui Torres",
      "postal_code": [
        "85223"
      ]
    },
    {
      "city": "Navojoa",
      "colonia": "Torobene",
      "postal_code": [
        "85228"
      ]
    },
    {
      "city": "Navojoa",
      "colonia": "Torocoba",
      "postal_code": [
        "85222"
      ]
    },
    {
      "city": "Navojoa",
      "colonia": "Tres Arbolitos",
      "postal_code": [
        "85234"
      ]
    },
    {
      "city": "Navojoa",
      "colonia": "Tres Hermanos",
      "postal_code": [
        "85237"
      ]
    },
    {
      "city": "Navojoa",
      "colonia": "Tres Jitos (Los Carrazco)",
      "postal_code": [
        "85224"
      ]
    },
    {
      "city": "Navojoa",
      "colonia": "Tucuri de Abajo",
      "postal_code": [
        "85239"
      ]
    },
    {
      "city": "Navojoa",
      "colonia": "Turi Kowi",
      "postal_code": [
        "85239"
      ]
    },
    {
      "city": "Navojoa",
      "colonia": "Ucamayo [Algodonera]",
      "postal_code": [
        "85225"
      ]
    },
    {
      "city": "Navojoa",
      "colonia": "Valle Buey",
      "postal_code": [
        "85230"
      ]
    },
    {
      "city": "Navojoa",
      "colonia": "Veintisiete",
      "postal_code": [
        "85224"
      ]
    },
    {
      "city": "Navojoa",
      "colonia": "Villa del Sol",
      "postal_code": [
        "85830"
      ]
    },
    {
      "city": "Navojoa",
      "colonia": "Villa Dorada",
      "postal_code": [
        "85874"
      ]
    },
    {
      "city": "Navojoa",
      "colonia": "Villa Lourdes",
      "postal_code": [
        "85825"
      ]
    },
    {
      "city": "Navojoa",
      "colonia": "Villas de Fatima",
      "postal_code": [
        "85870"
      ]
    },
    {
      "city": "Navojoa",
      "colonia": "Vivajimari",
      "postal_code": [
        "85239"
      ]
    },
    {
      "city": "Navojoa",
      "colonia": "Yopari",
      "postal_code": [
        "85222"
      ]
    },
    {
      "city": "Navojoa",
      "colonia": "Yorentamehua",
      "postal_code": [
        "85239"
      ]
    },
    {
      "city": "Navojoa",
      "colonia": "Yorimayo",
      "postal_code": [
        "85224"
      ]
    }
  ]
}