{
  "data": [
    {
      "city": "San Lucas Tecopilco",
      "colonia": "Cauatla",
      "postal_code": [
        "90448"
      ]
    },
    {
      "city": "San Lucas Tecopilco",
      "colonia": "El Llano",
      "postal_code": [
        "90447"
      ]
    },
    {
      "city": "San Lucas Tecopilco",
      "colonia": "Las Canadas",
      "postal_code": [
        "90446"
      ]
    },
    {
      "city": "San Lucas Tecopilco",
      "colonia": "Loma Bonita",
      "postal_code": [
        "90448"
      ]
    },
    {
      "city": "San Lucas Tecopilco",
      "colonia": "San Jose Rosastitla",
      "postal_code": [
        "90448"
      ]
    },
    {
      "city": "San Lucas Tecopilco",
      "colonia": "San Lucas Tecopilco",
      "postal_code": [
        "90445"
      ]
    },
    {
      "city": "San Lucas Tecopilco",
      "colonia": "Tlaxcantitla",
      "postal_code": [
        "90448"
      ]
    },
    {
      "city": "San Lucas Tecopilco",
      "colonia": "Toltecapa",
      "postal_code": [
        "90446"
      ]
    }
  ]
}