{
  "data": [
    {
      "city": "Uman",
      "colonia": "Acim I",
      "postal_code": [
        "97390"
      ]
    },
    {
      "city": "Uman",
      "colonia": "Acim II",
      "postal_code": [
        "97390"
      ]
    },
    {
      "city": "Uman",
      "colonia": "Ampliacion Ciudad Industrial",
      "postal_code": [
        "97390"
      ]
    },
    {
      "city": "Uman",
      "colonia": "Bolon",
      "postal_code": [
        "97397"
      ]
    },
    {
      "city": "Uman",
      "colonia": "Bosques de San Francisco",
      "postal_code": [
        "97390"
      ]
    },
    {
      "city": "Uman",
      "colonia": "Bosques de Uman",
      "postal_code": [
        "97390"
      ]
    },
    {
      "city": "Uman",
      "colonia": "Brisas de Uman",
      "postal_code": [
        "97390"
      ]
    },
    {
      "city": "Uman",
      "colonia": "Camino Real",
      "postal_code": [
        "97390"
      ]
    },
    {
      "city": "Uman",
      "colonia": "Centro Uman",
      "postal_code": [
        "97390"
      ]
    },
    {
      "city": "Uman",
      "colonia": "Cepeda Peraza",
      "postal_code": [
        "97390"
      ]
    },
    {
      "city": "Uman",
      "colonia": "Dzibikak",
      "postal_code": [
        "97393"
      ]
    },
    {
      "city": "Uman",
      "colonia": "Dzibikal",
      "postal_code": [
        "97390"
      ]
    },
    {
      "city": "Uman",
      "colonia": "El Oasis",
      "postal_code": [
        "97390"
      ]
    },
    {
      "city": "Uman",
      "colonia": "El Roble Agricola IV",
      "postal_code": [
        "97392"
      ]
    },
    {
      "city": "Uman",
      "colonia": "Gran Santa Cruz",
      "postal_code": [
        "97394"
      ]
    },
    {
      "city": "Uman",
      "colonia": "Hotzuc",
      "postal_code": [
        "97395"
      ]
    },
    {
      "city": "Uman",
      "colonia": "Itzincab",
      "postal_code": [
        "97392"
      ]
    },
    {
      "city": "Uman",
      "colonia": "La Candelaria",
      "postal_code": [
        "97390"
      ]
    },
    {
      "city": "Uman",
      "colonia": "La Mejorada",
      "postal_code": [
        "97390"
      ]
    },
    {
      "city": "Uman",
      "colonia": "Las Perlas de Uman",
      "postal_code": [
        "97390"
      ]
    },
    {
      "city": "Uman",
      "colonia": "Lazaro Cardenas",
      "postal_code": [
        "97390"
      ]
    },
    {
      "city": "Uman",
      "colonia": "Los Arcos I",
      "postal_code": [
        "97390"
      ]
    },
    {
      "city": "Uman",
      "colonia": "Los Arcos II",
      "postal_code": [
        "97390"
      ]
    },
    {
      "city": "Uman",
      "colonia": "Los Ceibos",
      "postal_code": [
        "97390"
      ]
    },
    {
      "city": "Uman",
      "colonia": "Miguel Hidalgo y Costilla",
      "postal_code": [
        "97390"
      ]
    },
    {
      "city": "Uman",
      "colonia": "Oxcum",
      "postal_code": [
        "97393"
      ]
    },
    {
      "city": "Uman",
      "colonia": "Oxholon",
      "postal_code": [
        "97397"
      ]
    },
    {
      "city": "Uman",
      "colonia": "Petecbiltun",
      "postal_code": [
        "97394"
      ]
    },
    {
      "city": "Uman",
      "colonia": "Piedra de Agua",
      "postal_code": [
        "97392"
      ]
    },
    {
      "city": "Uman",
      "colonia": "Poxila",
      "postal_code": [
        "97397"
      ]
    },
    {
      "city": "Uman",
      "colonia": "Residencial San Lazaro",
      "postal_code": [
        "97390"
      ]
    },
    {
      "city": "Uman",
      "colonia": "San Antonio Chun",
      "postal_code": [
        "97397"
      ]
    },
    {
      "city": "Uman",
      "colonia": "San Antonio Mulix",
      "postal_code": [
        "97396"
      ]
    },
    {
      "city": "Uman",
      "colonia": "San Carlos",
      "postal_code": [
        "97390"
      ]
    },
    {
      "city": "Uman",
      "colonia": "San Lorenzo",
      "postal_code": [
        "97390"
      ]
    },
    {
      "city": "Uman",
      "colonia": "Santa Elena",
      "postal_code": [
        "97390"
      ]
    },
    {
      "city": "Uman",
      "colonia": "Tanil",
      "postal_code": [
        "97394"
      ]
    },
    {
      "city": "Uman",
      "colonia": "Tebec",
      "postal_code": [
        "97394"
      ]
    },
    {
      "city": "Uman",
      "colonia": "Ticimul",
      "postal_code": [
        "97394"
      ]
    },
    {
      "city": "Uman",
      "colonia": "Xcucul Sur",
      "postal_code": [
        "97394"
      ]
    },
    {
      "city": "Uman",
      "colonia": "Xtepen",
      "postal_code": [
        "97394"
      ]
    },
    {
      "city": "Uman",
      "colonia": "Yaxcopoil",
      "postal_code": [
        "97396"
      ]
    }
  ]
}